Workbook

Sheet Work Component  Split
C2: Work Allocation
D3: Seniors Review | E3: Accountants Work | F3: Bookkeeper's Work
C4: Management Accounts | D4: 0.1 | E4: 0.4 | F4: 0.5
C5: Payroll | D5: 0.1 | E5: 0.9 | F5: 0
C6: Once Off Work | D6: 0.1 | E6: 0.9 | F6: 0
C9: Client | D9: Payroll (Cost Incl) | E9: Management accounts (Cost Incl) | F9: Total Amount (Cost Excl) | G9: P: Reviewer | H9: P: Accountant | I9: MA: Bookkeeper | J9: MA: Accountant | K9: MA: Reviewer | L9: % total
C10: Maxopani Holdings | D10: =7948.8*100/115 -> 6912 | E10: =18600/1.15 -> 16173.913 | F10: 23085.91 | G10: =(D10*$D$5)/F10 -> 0.02994034 | H10: =(D10*$E$5)/F10 -> 0.26946306 | I10: =(E10*$F$4)/F10 -> 0.35029836 | J10: =(E10*$E$4)/F10 -> 0.28023869 | K10: =(E10*$D$4)/F10 -> 0.070059673 | L10: =K10+J10+I10+H10+G10 -> 1.0000001 | N10: 1.15
C11: Sinet Africa | D11: 0 | E11: =4968/1.15 -> 4320 | F11: 4320 | G11: =(D11*$D$5)/F11 -> 0 | H11: =(D11*$E$5)/F11 -> 0 | I11: =(E11*$F$4)/F11 -> 0.5 | J11: =(E11*$E$4)/F11 -> 0.4 | K11: =(E11*$D$4)/F11 -> 0.1 | L11: =K11+J11+I11+H11+G11 -> 1
C12: Innovateher | D12: 0 | E12: =28444.5108/1.15 -> 24734.357 | F12: 24734.36 | G12: =(D12*$D$5)/F12 -> 0 | H12: =(D12*$E$5)/F12 -> 0 | I12: =(E12*$F$4)/F12 -> 0.49999994 | J12: =(E12*$E$4)/F12 -> 0.39999996 | K12: =(E12*$D$4)/F12 -> 0.099999989 | L12: =K12+J12+I12+H12+G12 -> 0.99999989
C13: Khulio Electric | D13: 0 | E13: =14904/1.15 -> 12960 | F13: 12960 | G13: =(D13*$D$5)/F13 -> 0 | H13: =(D13*$E$5)/F13 -> 0 | I13: =(E13*$F$4)/F13 -> 0.5 | J13: =(E13*$E$4)/F13 -> 0.4 | K13: =(E13*$D$4)/F13 -> 0.1 | L13: =K13+J13+I13+H13+G13 -> 1
C14: Hambo Lwethu | D14: 0 | E14: =5302.098/1.15 -> 4610.52 | F14: 4610.52 | G14: =(D14*$D$5)/F14 -> 0 | H14: =(D14*$E$5)/F14 -> 0 | I14: =(E14*$F$4)/F14 -> 0.5 | J14: =(E14*$E$4)/F14 -> 0.4 | K14: =(E14*$D$4)/F14 -> 0.1 | L14: =K14+J14+I14+H14+G14 -> 1
C15: Spade | D15: 0 | E15: 0 | F15: =E15+D15 -> 0 | G15: =(D15*$D$5)/F15 -> #DIV/0! | H15: =(D15*$E$5)/F15 -> #DIV/0! | I15: =(E15*$F$4)/F15 -> #DIV/0! | J15: =(E15*$E$4)/F15 -> #DIV/0! | K15: =(E15*$D$4)/F15 -> #DIV/0! | L15: =K15+J15+I15+H15+G15 -> #DIV/0!
C16: Makhubela Incorporated | D16: =500/1.15 -> 434.78261 | E16: =1851.77/1.15 -> 1610.2348 | F16: 2045.02 | G16: =(D16*$D$5)/F16 -> 0.021260555 | H16: =(D16*$E$5)/F16 -> 0.191345 | I16: =(E16*$F$4)/F16 -> 0.39369659 | J16: =(E16*$E$4)/F16 -> 0.31495727 | K16: =(E16*$D$4)/F16 -> 0.078739317 | L16: =K16+J16+I16+H16+G16 -> 0.99999872
C17: Destiny Finance (Pty) Ltd | D17: =3585.14/1.15 -> 3117.513 | E17: =6613.65/1.15 -> 5751 | F17: 8868.51 | G17: =(D17*$D$5)/F17 -> 0.035152613 | H17: =(D17*$E$5)/F17 -> 0.31637352 | I17: =(E17*$F$4)/F17 -> 0.3242371 | J17: =(E17*$E$4)/F17 -> 0.25938968 | K17: =(E17*$D$4)/F17 -> 0.064847421 | L17: =K17+J17+I17+H17+G17 -> 1.0000003
C18: DR WW NGWATA PRACTICE INC | D18: =460/1.15 -> 400 | E18: =3189.02/1.15 -> 2773.0609 | F18: 3173.06 | G18: =(D18*$D$5)/F18 -> 0.012606128 | H18: =(D18*$E$5)/F18 -> 0.11345515 | I18: =(E18*$F$4)/F18 -> 0.4369695 | J18: =(E18*$E$4)/F18 -> 0.3495756 | K18: =(E18*$D$4)/F18 -> 0.0873939 | L18: =K18+J18+I18+H18+G18 -> 1.0000003
C19: Bixa Consulting | D19: =500/1.15 -> 434.78261 | E19: =2794.5/1.15 -> 2430 | F19: 2864.78 | G19: =(D19*$D$5)/F19 -> 0.015176824 | H19: =(D19*$E$5)/F19 -> 0.13659141 | I19: =(E19*$F$4)/F19 -> 0.42411634 | J19: =(E19*$E$4)/F19 -> 0.33929307 | K19: =(E19*$D$4)/F19 -> 0.084823267 | L19: =K19+J19+I19+H19+G19 -> 1.0000009
C20: Mvundlane | D20: 0 | E20: =3105/1.15 -> 2700 | F20: 2700 | G20: =(D20*$D$5)/F20 -> 0 | H20: =(D20*$E$5)/F20 -> 0 | I20: =(E20*$F$4)/F20 -> 0.5 | J20: =(E20*$E$4)/F20 -> 0.4 | K20: =(E20*$D$4)/F20 -> 0.1 | L20: =K20+J20+I20+H20+G20 -> 1
C21: Solid Re Global | D21: 0 | E21: =2916/1.15 -> 2535.6522 | F21: 2535.65 | G21: =(D21*$D$5)/F21 -> 0 | H21: =(D21*$E$5)/F21 -> 0 | I21: =(E21*$F$4)/F21 -> 0.50000043 | J21: =(E21*$E$4)/F21 -> 0.40000034 | K21: =(E21*$D$4)/F21 -> 0.10000009 | L21: =K21+J21+I21+H21+G21 -> 1.0000009
C22: Drs Koranteng | D22: 0 | E22: =3050.14/1.15 -> 2652.2957 | F22: 2652.29 | G22: =(D22*$D$5)/F22 -> 0 | H22: =(D22*$E$5)/F22 -> 0 | I22: =(E22*$F$4)/F22 -> 0.50000107 | J22: =(E22*$E$4)/F22 -> 0.40000085 | K22: =(E22*$D$4)/F22 -> 0.10000021 | L22: =K22+J22+I22+H22+G22 -> 1.0000021
C23: Destiny Portfolio | D23: 0 | E23: =4448.84/1.15 -> 3868.5565 | F23: 3868.56 | G23: =(D23*$D$5)/F23 -> 0 | H23: =(D23*$E$5)/F23 -> 0 | I23: =(E23*$F$4)/F23 -> 0.49999955 | J23: =(E23*$E$4)/F23 -> 0.39999964 | K23: =(E23*$D$4)/F23 -> 0.09999991 | L23: =K23+J23+I23+H23+G23 -> 0.9999991
C24: Giant Bee Logistics Pty Ltd | D24: =1252.42/1.15 -> 1089.0609 | E24: =5410.15/1.15 -> 4704.4783 | F24: 5793.54 | G24: =(D24*$D$5)/F24 -> 0.018797848 | H24: =(D24*$E$5)/F24 -> 0.16918064 | I24: =(E24*$F$4)/F24 -> 0.40601068 | J24: =(E24*$E$4)/F24 -> 0.32480855 | K24: =(E24*$D$4)/F24 -> 0.081202137 | L24: =K24+J24+I24+H24+G24 -> 0.99999985
C25: Pono Vision Radiology | D25: 0 | E25: =2052/1.15 -> 1784.3478 | F25: 1784.35 | G25: =(D25*$D$5)/F25 -> 0 | H25: =(D25*$E$5)/F25 -> 0 | I25: =(E25*$F$4)/F25 -> 0.49999939 | J25: =(E25*$E$4)/F25 -> 0.39999951 | K25: =(E25*$D$4)/F25 -> 0.099999878 | L25: =K25+J25+I25+H25+G25 -> 0.99999878
C26: Achri | D26: 0 | E26: =16121.16/1.15 -> 14018.4 | F26: 14018.4 | G26: =(D26*$D$5)/F26 -> 0 | H26: =(D26*$E$5)/F26 -> 0 | I26: =(E26*$F$4)/F26 -> 0.5 | J26: =(E26*$E$4)/F26 -> 0.4 | K26: =(E26*$D$4)/F26 -> 0.1 | L26: =K26+J26+I26+H26+G26 -> 1
C27: Astra Matellite | D27: =2190.0375/1.15 -> 1904.3804 | E27: =3937.5/1.15 -> 3423.913 | F27: 5328.2935 | G27: =(D27*$D$5)/F27 -> 0.035740907 | H27: =(D27*$E$5)/F27 -> 0.32166817 | I27: =(E27*$F$4)/F27 -> 0.32129546 | J27: =(E27*$E$4)/F27 -> 0.25703637 | K27: =(E27*$D$4)/F27 -> 0.064259093 | L27: =K27+J27+I27+H27+G27 -> 1
C28: Advocate Maputla | D28: 0 | E28: =28959.12/1.15 -> 25181.843 | F28: 25181.84 | G28: =(D28*$D$5)/F28 -> 0 | H28: =(D28*$E$5)/F28 -> 0 | I28: =(E28*$F$4)/F28 -> 0.50000007 | J28: =(E28*$E$4)/F28 -> 0.40000006 | K28: =(E28*$D$4)/F28 -> 0.10000001 | L28: =K28+J28+I28+H28+G28 -> 1.0000001
C29: CREATIVE VALLEY NURSERY SCHOOL | D29: =1075/1.15 -> 934.78261 | E29: =2368.7748/1.15 -> 2059.8042 | F29: 2994.59 | G29: =(D29*$D$5)/F29 -> 0.031215713 | H29: =(D29*$E$5)/F29 -> 0.28094141 | I29: =(E29*$F$4)/F29 -> 0.3439209 | J29: =(E29*$E$4)/F29 -> 0.27513672 | K29: =(E29*$D$4)/F29 -> 0.06878418 | L29: =K29+J29+I29+H29+G29 -> 0.99999893
C30: Depesh Cara | D30: =540/1.15 -> 469.56522 | E30: 3478.2608 | F30: =E30+D30 -> 3947.826 | G30: =(D30*$D$5)/F30 -> 0.011894273 | H30: =(D30*$E$5)/F30 -> 0.10704846 | I30: =(E30*$F$4)/F30 -> 0.44052863 | J30: =(E30*$E$4)/F30 -> 0.35242291 | K30: =(E30*$D$4)/F30 -> 0.088105727 | L30: =K30+J30+I30+H30+G30 -> 1
C31: Dr A.S Bajomo | D31: =550/1.15 -> 478.26087 | E31: =4089.852/1.15 -> 3556.393 | F31: 4034.65 | G31: =(D31*$D$5)/F31 -> 0.011853838 | H31: =(D31*$E$5)/F31 -> 0.10668454 | I31: =(E31*$F$4)/F31 -> 0.4407313 | J31: =(E31*$E$4)/F31 -> 0.35258504 | K31: =(E31*$D$4)/F31 -> 0.088146259 | L31: =K31+J31+I31+H31+G31 -> 1.000001
C32: Katomax Investments | D32: 0 | E32: =2916.0216/1.15 -> 2535.671 | F32: 2535.67 | G32: =(D32*$D$5)/F32 -> 0 | H32: =(D32*$E$5)/F32 -> 0 | I32: =(E32*$F$4)/F32 -> 0.50000019 | J32: =(E32*$E$4)/F32 -> 0.40000015 | K32: =(E32*$D$4)/F32 -> 0.10000004 | L32: =K32+J32+I32+H32+G32 -> 1.0000004
C33: New Orlscade | D33: 0 | E33: =8694/1.15 -> 7560 | F33: 7560 | G33: =(D33*$D$5)/F33 -> 0 | H33: =(D33*$E$5)/F33 -> 0 | I33: =(E33*$F$4)/F33 -> 0.5 | J33: =(E33*$E$4)/F33 -> 0.4 | K33: =(E33*$D$4)/F33 -> 0.1 | L33: =K33+J33+I33+H33+G33 -> 1
C34: Rentals Proper team Fourways | D34: 0 | E34: =3936.6/1.15 -> 3423.1304 | F34: 3423.13 | G34: =(D34*$D$5)/F34 -> 0 | H34: =(D34*$E$5)/F34 -> 0 | I34: =(E34*$F$4)/F34 -> 0.50000006 | J34: =(E34*$E$4)/F34 -> 0.40000005 | K34: =(E34*$D$4)/F34 -> 0.10000001 | L34: =K34+J34+I34+H34+G34 -> 1.0000001
C35: TMM TECH | D35: 0 | E35: =4082.4/1.15 -> 3549.913 | F35: 3549.91 | G35: =(D35*$D$5)/F35 -> 0 | H35: =(D35*$E$5)/F35 -> 0 | I35: =(E35*$F$4)/F35 -> 0.50000043 | J35: =(E35*$E$4)/F35 -> 0.40000034 | K35: =(E35*$D$4)/F35 -> 0.10000009 | L35: =K35+J35+I35+H35+G35 -> 1.0000009
C36: Mectech Motors | D36: =1251.936/1.15 -> 1088.64 | E36: =6095.736/1.15 -> 5300.64 | F36: 6389.28 | G36: =(D36*$D$5)/F36 -> 0.01703854 | H36: =(D36*$E$5)/F36 -> 0.15334686 | I36: =(E36*$F$4)/F36 -> 0.4148073 | J36: =(E36*$E$4)/F36 -> 0.33184584 | K36: =(E36*$D$4)/F36 -> 0.08296146 | L36: =K36+J36+I36+H36+G36 -> 1
C37: Blue Hill | D37: =700/1.15 -> 608.69565 | E37: =3780/1.15 -> 3286.9565 | F37: 3895.65 | G37: =(D37*$D$5)/F37 -> 0.015625009 | H37: =(D37*$E$5)/F37 -> 0.14062508 | I37: =(E37*$F$4)/F37 -> 0.42187524 | J37: =(E37*$E$4)/F37 -> 0.33750019 | K37: =(E37*$D$4)/F37 -> 0.084375047 | L37: =K37+J37+I37+H37+G37 -> 1.0000006
C38: Chemstrat | D38: 0 | E38: =16146/1.15 -> 14040 | F38: 14040 | G38: =(D38*$D$5)/F38 -> 0 | H38: =(D38*$E$5)/F38 -> 0 | I38: =(E38*$F$4)/F38 -> 0.5 | J38: =(E38*$E$4)/F38 -> 0.4 | K38: =(E38*$D$4)/F38 -> 0.1 | L38: =K38+J38+I38+H38+G38 -> 1
C39: R Protections | D39: 0 | E39: =9315/1.15 -> 8100 | F39: 8100 | G39: =(D39*$D$5)/F39 -> 0 | H39: =(D39*$E$5)/F39 -> 0 | I39: =(E39*$F$4)/F39 -> 0.5 | J39: =(E39*$E$4)/F39 -> 0.4 | K39: =(E39*$D$4)/F39 -> 0.1 | L39: =K39+J39+I39+H39+G39 -> 1
C40: Fitness Reenvisioned | D40: 0 | E40: =1807.92/1.15 -> 1572.1043 | F40: 1572.1 | G40: =(D40*$D$5)/F40 -> 0 | H40: =(D40*$E$5)/F40 -> 0 | I40: =(E40*$F$4)/F40 -> 0.50000138 | J40: =(E40*$E$4)/F40 -> 0.40000111 | K40: =(E40*$D$4)/F40 -> 0.10000028 | L40: =K40+J40+I40+H40+G40 -> 1.0000028
C41: Luk Capital | D41: 0 | E41: =2985.984/1.15 -> 2596.5078 | F41: 2596.51 | G41: =(D41*$D$5)/F41 -> 0 | H41: =(D41*$E$5)/F41 -> 0 | I41: =(E41*$F$4)/F41 -> 0.49999958 | J41: =(E41*$E$4)/F41 -> 0.39999967 | K41: =(E41*$D$4)/F41 -> 0.099999916 | L41: =K41+J41+I41+H41+G41 -> 0.99999916
C42: Moja Legal Consulting and Investment (Pty) Ltd | D42: 0 | E42: =2332.8/1.15 -> 2028.5217 | F42: 2028.52 | G42: =(D42*$D$5)/F42 -> 0 | H42: =(D42*$E$5)/F42 -> 0 | I42: =(E42*$F$4)/F42 -> 0.50000043 | J42: =(E42*$E$4)/F42 -> 0.40000034 | K42: =(E42*$D$4)/F42 -> 0.10000009 | L42: =K42+J42+I42+H42+G42 -> 1.0000009
C43: Vera Step | D43: 0 | E43: =3384.45/1.15 -> 2943 | F43: 2943 | G43: =(D43*$D$5)/F43 -> 0 | H43: =(D43*$E$5)/F43 -> 0 | I43: =(E43*$F$4)/F43 -> 0.5 | J43: =(E43*$E$4)/F43 -> 0.4 | K43: =(E43*$D$4)/F43 -> 0.1 | L43: =K43+J43+I43+H43+G43 -> 1
C44: Natasha Mohunlal | D44: =496.8/1.15 -> 432 | E44: =2116.8/1.15 -> 1840.6957 | F44: 2272.7 | G44: =(D44*$D$5)/F44 -> 0.019008228 | H44: =(D44*$E$5)/F44 -> 0.17107405 | I44: =(E44*$F$4)/F44 -> 0.4049579 | J44: =(E44*$E$4)/F44 -> 0.32396632 | K44: =(E44*$D$4)/F44 -> 0.080991581 | L44: =K44+J44+I44+H44+G44 -> 0.99999809
C45: Swiiff | D45: 0 | E45: =3353.4/1.15 -> 2916 | F45: 2916 | G45: =(D45*$D$5)/F45 -> 0 | H45: =(D45*$E$5)/F45 -> 0 | I45: =(E45*$F$4)/F45 -> 0.5 | J45: =(E45*$E$4)/F45 -> 0.4 | K45: =(E45*$D$4)/F45 -> 0.1 | L45: =K45+J45+I45+H45+G45 -> 1
C46: Mawela Simpson | D46: 0 | E46: =4471.2/1.15 -> 3888 | F46: 3888 | G46: =(D46*$D$5)/F46 -> 0 | H46: =(D46*$E$5)/F46 -> 0 | I46: =(E46*$F$4)/F46 -> 0.5 | J46: =(E46*$E$4)/F46 -> 0.4 | K46: =(E46*$D$4)/F46 -> 0.1 | L46: =K46+J46+I46+H46+G46 -> 1
C47: MGI Global | D47: 0 | E47: =3353.4/1.15 -> 2916 | F47: 2916 | G47: =(D47*$D$5)/F47 -> 0 | H47: =(D47*$E$5)/F47 -> 0 | I47: =(E47*$F$4)/F47 -> 0.5 | J47: =(E47*$E$4)/F47 -> 0.4 | K47: =(E47*$D$4)/F47 -> 0.1 | L47: =K47+J47+I47+H47+G47 -> 1
C48: MMFS | D48: =460/1.15 -> 400 | E48: =4347/1.15 -> 3780 | F48: 4180 | G48: =(D48*$D$5)/F48 -> 0.009569378 | H48: =(D48*$E$5)/F48 -> 0.086124402 | I48: =(E48*$F$4)/F48 -> 0.45215311 | J48: =(E48*$E$4)/F48 -> 0.36172249 | K48: =(E48*$D$4)/F48 -> 0.090430622 | L48: =K48+J48+I48+H48+G48 -> 1
C49: Bona By Wenzy | D49: 0 | E49: =2173.5/1.15 -> 1890 | F49: 1890 | G49: =(D49*$D$5)/F49 -> 0 | H49: =(D49*$E$5)/F49 -> 0 | I49: =(E49*$F$4)/F49 -> 0.5 | J49: =(E49*$E$4)/F49 -> 0.4 | K49: =(E49*$D$4)/F49 -> 0.1 | L49: =K49+J49+I49+H49+G49 -> 1
C50: Recovery Advisors | D50: 0 | E50: =2794.5/1.15 -> 2430 | F50: 2430 | G50: =(D50*$D$5)/F50 -> 0 | H50: =(D50*$E$5)/F50 -> 0 | I50: =(E50*$F$4)/F50 -> 0.5 | J50: =(E50*$E$4)/F50 -> 0.4 | K50: =(E50*$D$4)/F50 -> 0.1 | L50: =K50+J50+I50+H50+G50 -> 1
C51: Subtream | D51: 0 | E51: =6155.352/1.15 -> 5352.48 | F51: 5352.48 | G51: =(D51*$D$5)/F51 -> 0 | H51: =(D51*$E$5)/F51 -> 0 | I51: =(E51*$F$4)/F51 -> 0.5 | J51: =(E51*$E$4)/F51 -> 0.4 | K51: =(E51*$D$4)/F51 -> 0.1 | L51: =K51+J51+I51+H51+G51 -> 1
C52: Plush Spaces | D52: =439.88/1.15 -> 382.50435 | E52: =2209.15/1.15 -> 1921 | F52: 2303.5043 | G52: =(D52*$D$5)/F52 -> 0.016605323 | H52: =(D52*$E$5)/F52 -> 0.14944791 | I52: =(E52*$F$4)/F52 -> 0.41697338 | J52: =(E52*$E$4)/F52 -> 0.33357871 | K52: =(E52*$D$4)/F52 -> 0.083394677 | L52: =K52+J52+I52+H52+G52 -> 1
C53: CM Freelancing (Pty) Ltd | D53: 0 | E53: =3722.9004/1.15 -> 3237.3047 | F53: 3237.3 | G53: =(D53*$D$5)/F53 -> 0 | H53: =(D53*$E$5)/F53 -> 0 | I53: =(E53*$F$4)/F53 -> 0.50000073 | J53: =(E53*$E$4)/F53 -> 0.40000058 | K53: =(E53*$D$4)/F53 -> 0.10000015 | L53: =K53+J53+I53+H53+G53 -> 1.0000015
C54: EKSN ENGINEERING | D54: 0 | E54: =2052.2808/1.15 -> 1784.592 | F54: 1784.59 | G54: =(D54*$D$5)/F54 -> 0 | H54: =(D54*$E$5)/F54 -> 0 | I54: =(E54*$F$4)/F54 -> 0.50000056 | J54: =(E54*$E$4)/F54 -> 0.40000045 | K54: =(E54*$D$4)/F54 -> 0.10000011 | L54: =K54+J54+I54+H54+G54 -> 1.0000011
C55: CN Freight | D55: =550/1.15 -> 478.26087 | E55: =4158.216/1.15 -> 3615.84 | F55: 4094.1 | G55: =(D55*$D$5)/F55 -> 0.01168171 | H55: =(D55*$E$5)/F55 -> 0.10513539 | I55: =(E55*$F$4)/F55 -> 0.44159156 | J55: =(E55*$E$4)/F55 -> 0.35327325 | K55: =(E55*$D$4)/F55 -> 0.088318312 | L55: =K55+J55+I55+H55+G55 -> 1.0000002
C56: Khayelihle Properties | D56: 0 | E56: 3240 | F56: 3240 | G56: =(D56*$D$5)/F56 -> 0 | H56: =(D56*$E$5)/F56 -> 0 | I56: =(E56*$F$4)/F56 -> 0.5 | J56: =(E56*$E$4)/F56 -> 0.4 | K56: =(E56*$D$4)/F56 -> 0.1 | L56: =K56+J56+I56+H56+G56 -> 1
C57: Ndana Investments | D57: 0 | E57: =1925.1/1.15 -> 1674 | F57: 1674 | G57: =(D57*$D$5)/F57 -> 0 | H57: =(D57*$E$5)/F57 -> 0 | I57: =(E57*$F$4)/F57 -> 0.5 | J57: =(E57*$E$4)/F57 -> 0.4 | K57: =(E57*$D$4)/F57 -> 0.1 | L57: =K57+J57+I57+H57+G57 -> 1
C58: Primetyme | D58: 0 | E58: =3042.9/1.15 -> 2646 | F58: 2646 | G58: =(D58*$D$5)/F58 -> 0 | H58: =(D58*$E$5)/F58 -> 0 | I58: =(E58*$F$4)/F58 -> 0.5 | J58: =(E58*$E$4)/F58 -> 0.4 | K58: =(E58*$D$4)/F58 -> 0.1 | L58: =K58+J58+I58+H58+G58 -> 1
C59: SRYC | D59: 0 | E59: =3042.9/1.15 -> 2646 | F59: 2646 | G59: =(D59*$D$5)/F59 -> 0 | H59: =(D59*$E$5)/F59 -> 0 | I59: =(E59*$F$4)/F59 -> 0.5 | J59: =(E59*$E$4)/F59 -> 0.4 | K59: =(E59*$D$4)/F59 -> 0.1 | L59: =K59+J59+I59+H59+G59 -> 1
C60: Mutsekwa Private Wealth | D60: 0 | E60: =1229.58/1.15 -> 1069.2 | F60: 1069.2 | G60: =(D60*$D$5)/F60 -> 0 | H60: =(D60*$E$5)/F60 -> 0 | I60: =(E60*$F$4)/F60 -> 0.5 | J60: =(E60*$E$4)/F60 -> 0.4 | K60: =(E60*$D$4)/F60 -> 0.1 | L60: =K60+J60+I60+H60+G60 -> 1
C61: JFM Private property | D61: 0 | E61: =1229.58/1.16 -> 1059.9828 | F61: =E61+D61 -> 1059.9828 | G61: =(D61*$D$5)/F61 -> 0 | H61: =(D61*$E$5)/F61 -> 0 | I61: =(E61*$F$4)/F61 -> 0.5 | J61: =(E61*$E$4)/F61 -> 0.4 | K61: =(E61*$D$4)/F61 -> 0.1 | L61: =K61+J61+I61+H61+G61 -> 1
C62: Promote Balance | D62: =496.8/1.15 -> 432 | E62: 0 | F62: 432 | G62: =(D62*$D$5)/F62 -> 0.1 | H62: =(D62*$E$5)/F62 -> 0.9 | I62: =(E62*$F$4)/F62 -> 0 | J62: =(E62*$E$4)/F62 -> 0 | K62: =(E62*$D$4)/F62 -> 0 | L62: =K62+J62+I62+H62+G62 -> 1
C63: Bophelong | D63: =2918.7/1.15 -> 2538 | E63: 0 | F63: 2538 | G63: =(D63*$D$5)/F63 -> 0.1 | H63: =(D63*$E$5)/F63 -> 0.9 | I63: =(E63*$F$4)/F63 -> 0 | J63: =(E63*$E$4)/F63 -> 0 | K63: =(E63*$D$4)/F63 -> 0 | L63: =K63+J63+I63+H63+G63 -> 1
C64: Makhubela Incorporated | D64: =500/1.15 -> 434.78261 | E64: =1851.77/1.15 -> 1610.2348 | F64: 2045.02 | G64: =(D64*$D$5)/F64 -> 0.021260555 | H64: =(D64*$E$5)/F64 -> 0.191345 | I64: =(E64*$F$4)/F64 -> 0.39369659 | J64: =(E64*$E$4)/F64 -> 0.31495727 | K64: =(E64*$D$4)/F64 -> 0.078739317 | L64: =K64+J64+I64+H64+G64 -> 0.99999872
C65: Maksure Risk Solutions | D65: =7781.4/1.15 -> 6766.4348 | E65: 0 | F65: 6766.43 | G65: =(D65*$D$5)/F65 -> 0.10000007 | H65: =(D65*$E$5)/F65 -> 0.90000064 | I65: =(E65*$F$4)/F65 -> 0 | J65: =(E65*$E$4)/F65 -> 0 | K65: =(E65*$D$4)/F65 -> 0 | L65: =K65+J65+I65+H65+G65 -> 1.0000007
C66: Maksure Zim | D66: =1944/1.15 -> 1690.4348 | E66: =5151.6/1.15 -> 4479.6522 | F66: 6170.09 | G66: =(D66*$D$5)/F66 -> 0.027397247 | H66: =(D66*$E$5)/F66 -> 0.24657522 | I66: =(E66*$F$4)/F66 -> 0.36301352 | J66: =(E66*$E$4)/F66 -> 0.29041082 | K66: =(E66*$D$4)/F66 -> 0.072602704 | L66: =K66+J66+I66+H66+G66 -> 0.99999951
C67: Maphosa Attorneys | D67: =819.72/1.15 -> 712.8 | E67: 0 | F67: 712.8 | G67: =(D67*$D$5)/F67 -> 0.1 | H67: =(D67*$E$5)/F67 -> 0.9 | I67: =(E67*$F$4)/F67 -> 0 | J67: =(E67*$E$4)/F67 -> 0 | K67: =(E67*$D$4)/F67 -> 0 | L67: =K67+J67+I67+H67+G67 -> 1
C68: Playroll Zimbabwe | D68: =1026/1.15 -> 892.17391 | E68: 0 | F68: 892.17 | G68: =(D68*$D$5)/F68 -> 0.10000044 | H68: =(D68*$E$5)/F68 -> 0.90000395 | I68: =(E68*$F$4)/F68 -> 0 | J68: =(E68*$E$4)/F68 -> 0 | K68: =(E68*$D$4)/F68 -> 0 | L68: =K68+J68+I68+H68+G68 -> 1.0000044
C69: RutotechSA | D69: =1214.4/1.15 -> 1056 | E69: 0 | F69: 1056 | G69: =(D69*$D$5)/F69 -> 0.1 | H69: =(D69*$E$5)/F69 -> 0.9 | I69: =(E69*$F$4)/F69 -> 0 | J69: =(E69*$E$4)/F69 -> 0 | K69: =(E69*$D$4)/F69 -> 0 | L69: =K69+J69+I69+H69+G69 -> 1
C70: Sinto | D70: =540/1.15 -> 469.56522 | E70: 0 | F70: 469.57 | G70: =(D70*$D$5)/F70 -> 0.099998981 | H70: =(D70*$E$5)/F70 -> 0.89999083 | I70: =(E70*$F$4)/F70 -> 0 | J70: =(E70*$E$4)/F70 -> 0 | K70: =(E70*$D$4)/F70 -> 0 | L70: =K70+J70+I70+H70+G70 -> 0.99998981
C71: Work co | D71: =993.6/1.15 -> 864 | E71: 0 | F71: 864 | G71: =(D71*$D$5)/F71 -> 0.1 | H71: =(D71*$E$5)/F71 -> 0.9 | I71: =(E71*$F$4)/F71 -> 0 | J71: =(E71*$E$4)/F71 -> 0 | K71: =(E71*$D$4)/F71 -> 0 | L71: =K71+J71+I71+H71+G71 -> 1
C72: Total: | D72: =SUM(D10:D71) -> 35421.42 | E72: =SUM(E10:E71) -> 256260.46 | F72: =SUM(F10:F71) -> 291681.86

Sheet Star Jan - Dec '26
F3: Workflow Scheduling
B8: "A business is a commercial profitable enterprise that runs without you"
C10: Workflow Dashboard
B11: Senior Client Manager In Charge : | G11: Mollen Mukuze
B12: Team Name: | G12: Star Bongowongo
B14: Team Member: | D14: Star | G14: Role: | J14: Senior Auditor
C15: Analysis: | E15: Fees: | G15: Analysis: | K15: Hours:
C16: Annual Fee Budget | E16: =85000*12 -> 1020000 | G16: Annual Budgeted Hours | K16: =E16/C32 -> 1457.1429
C17: Scheduled Work and Jobs | E17: =+I88+I174+I243+I313+I383+I453+I523+I593+I663+I733+I803+I873 -> 38502.92 | G17: Scheduled Hours | K17: =+J88+J174+J243+J313+J383+J453+J523+J593+J663+J733+J803+J873 -> 55.004171
C18: Over (Under) Scheduled Work | E18: =E17-E16 -> -981497.08 | G18: Over (Under) Scheduled Work | K18: =K17-K16 -> -1402.1387
B20: Remaining Hours to Fill:
D21: January | E21: =J32 -> 114.01106 | F21: Apr | G21: =+J251 -> 121.6 | H21: July | I21: =+J461 -> 134.4 | J21: Oct | K21: =+J671 -> 147.2
D22: Feb | E22: =+J97 -> 93.384773 | F22: May | G22: =+J321 -> 140.8 | H22: Aug | I22: =J531 -> 134.4 | J22: Nov | K22: =+J741 -> 128
D23: Mar | E23: =+J182 -> 134.4 | F23: June | G23: =+J391 -> 128 | H23: Sept | I23: =+J601 -> 134.4 | J23: Dec | K23: =+J811 -> 128
B25: Total Productivity Hours To Fill : | G25: =SUM(E21:E23)+SUM(G21:G23)+SUM(I21:I23)+SUM(K21:K23) -> 1538.5958
C30: Workflow Schedule for | E30: January | J30: 2026
C31: Charge Rate: | D31: Working Days in Month | F31: KPI % | G31: Hours per Day | H31: Monthly Budgeted Hours | I31: Total Scheduled Fees | J31: Hours Left
C32: 700 | D32: 21 | F32: 0.8 | G32: 8 | H32: =D32*G32*F32 -> 134.4 | I32: =I88 -> 14272.261 | J32: =H32-J88 -> 114.01106
C33: Entity Group \ Job Name | D33: Notes | F33: Estimated Fees for Job | G33: Team Members Job Completion % | H33: Pricing or Efficiency Override | I33: Budgeted WIP | J33: Job Budgeted Hrs | K33: Submission Date to client | L33: Accountants commnent on Due Date
C35: Monthly Recurring Work
C36: Management Accounts:
B37: 1 | C37: Innovateher | F37: ='Work Component Split'!F12 -> 24734.36 | G37: ='Work Component Split'!K12 -> 0.099999989 | H37: 1 | I37: =J37*$C$32 -> 2473.4357 | J37: =(F37*G37*H37)/$C$32 -> 3.5334796
B38: =B37+1 -> 2 | C38: Makhubela Incorporated | F38: ='Work Component Split'!F16 -> 2045.02 | G38: ='Work Component Split'!K16 -> 0.078739317 | H38: 1 | I38: =J38*$C$32 -> 161.02348 | J38: =(F38*G38*H38)/$C$32 -> 0.23003354
B39: =B38+1 -> 3 | C39: Destiny Finance (Pty) Ltd | F39: ='Work Component Split'!F17 -> 8868.51 | G39: ='Work Component Split'!K17 -> 0.064847421 | H39: 1 | I39: =J39*$C$32 -> 575.1 | J39: =(F39*G39*H39)/$C$32 -> 0.82157143
B40: =B39+1 -> 4 | C40: DR WW NGWATA PRACTICE INC | F40: ='Work Component Split'!F18 -> 3173.06 | G40: ='Work Component Split'!K18 -> 0.0873939 | H40: 1 | I40: =J40*$C$32 -> 277.30609 | J40: =(F40*G40*H40)/$C$32 -> 0.39615155
B41: =B40+1 -> 5 | C41: Bixa Consulting | F41: ='Work Component Split'!F19 -> 2864.78 | G41: ='Work Component Split'!K19 -> 0.084823267 | H41: 1 | I41: =J41*$C$32 -> 243 | J41: =(F41*G41*H41)/$C$32 -> 0.34714286
B42: =B41+1 -> 6 | C42: Mvundlane | F42: ='Work Component Split'!F20 -> 2700 | G42: ='Work Component Split'!K20 -> 0.1 | H42: 1 | I42: =J42*$C$32 -> 270 | J42: =(F42*G42*H42)/$C$32 -> 0.38571429
B43: =B42+1 -> 7 | C43: Solid Re Global | F43: ='Work Component Split'!F21 -> 2535.65 | G43: ='Work Component Split'!K21 -> 0.10000009 | H43: 1 | I43: =J43*$C$32 -> 253.56522 | J43: =(F43*G43*H43)/$C$32 -> 0.36223602
B44: =B43+1 -> 8 | C44: Drs Koranteng | F44: ='Work Component Split'!F22 -> 2652.29 | G44: ='Work Component Split'!K22 -> 0.10000021 | H44: 1 | I44: =J44*$C$32 -> 265.22957 | J44: =(F44*G44*H44)/$C$32 -> 0.37889938
B45: =B44+1 -> 9 | C45: Destiny Portfolio | F45: ='Work Component Split'!F23 -> 3868.56 | G45: ='Work Component Split'!K23 -> 0.09999991 | H45: 1 | I45: =J45*$C$32 -> 386.85565 | J45: =(F45*G45*H45)/$C$32 -> 0.55265093
B46: =B45+1 -> 10 | C46: Giant Bee Logistics Pty Ltd | F46: ='Work Component Split'!F24 -> 5793.54 | G46: ='Work Component Split'!K24 -> 0.081202137 | H46: 1 | I46: =J46*$C$32 -> 470.44783 | J46: =(F46*G46*H46)/$C$32 -> 0.67206832
B47: =B46+1 -> 11 | C47: Pono Vision Radiology | F47: ='Work Component Split'!F25 -> 1784.35 | G47: ='Work Component Split'!K25 -> 0.099999878 | H47: 1 | I47: =J47*$C$32 -> 178.43478 | J47: =(F47*G47*H47)/$C$32 -> 0.25490683
B48: =B47+1 -> 12 | C48: Achri | F48: ='Work Component Split'!F26 -> 14018.4 | G48: ='Work Component Split'!K26 -> 0.1 | H48: 1 | I48: =J48*$C$32 -> 1401.84 | J48: =(F48*G48*H48)/$C$32 -> 2.0026286
B49: =B48+1 -> 13 | C49: Astra Matellite | F49: ='Work Component Split'!F27 -> 5328.2935 | G49: ='Work Component Split'!K27 -> 0.064259093 | H49: 1 | I49: =J49*$C$32 -> 342.3913 | J49: =(F49*G49*H49)/$C$32 -> 0.48913043
B50: =B49+1 -> 14 | C50: CREATIVE VALLEY NURSERY SCHOOL | F50: ='Work Component Split'!F29 -> 2994.59 | G50: ='Work Component Split'!K29 -> 0.06878418 | H50: 1 | I50: =J50*$C$32 -> 205.98042 | J50: =(F50*G50*H50)/$C$32 -> 0.29425774
B51: =B50+1 -> 15 | C51: Katomax Investments | F51: ='Work Component Split'!F31 -> 4034.65 | G51: ='Work Component Split'!K31 -> 0.088146259 | H51: 1 | I51: =J51*$C$32 -> 355.6393 | J51: =(F51*G51*H51)/$C$32 -> 0.50805615
B52: =B51+1 -> 16 | C52: Mectech Motors | F52: ='Work Component Split'!F35 -> 3549.91 | G52: ='Work Component Split'!K35 -> 0.10000009 | H52: 1 | I52: =J52*$C$32 -> 354.9913 | J52: =(F52*G52*H52)/$C$32 -> 0.50713043
B53: =B52+1 -> 17 | C53: Chemstrat | F53: ='Work Component Split'!F37 -> 3895.65 | G53: ='Work Component Split'!K37 -> 0.084375047 | H53: 1 | I53: =J53*$C$32 -> 328.69565 | J53: =(F53*G53*H53)/$C$32 -> 0.46956522
B54: =B53+1 -> 18 | C54: Fitness Reenvisioned | F54: ='Work Component Split'!F39 -> 8100 | G54: ='Work Component Split'!K39 -> 0.1 | H54: 1 | I54: =J54*$C$32 -> 810 | J54: =(F54*G54*H54)/$C$32 -> 1.1571429
B55: =B54+1 -> 19 | C55: Luk Capital | F55: ='Work Component Split'!F40 -> 1572.1 | G55: ='Work Component Split'!K40 -> 0.10000028 | H55: 1 | I55: =J55*$C$32 -> 157.21043 | J55: =(F55*G55*H55)/$C$32 -> 0.22458634
B56: =B55+1 -> 20 | C56: Moja Legal Consulting and Investment (Pty) Ltd | F56: ='Work Component Split'!F41 -> 2596.51 | G56: ='Work Component Split'!K41 -> 0.099999916 | H56: 1 | I56: =J56*$C$32 -> 259.65078 | J56: =(F56*G56*H56)/$C$32 -> 0.37092969
B57: =B56+1 -> 21 | C57: Vera Step | F57: ='Work Component Split'!F42 -> 2028.52 | G57: ='Work Component Split'!K42 -> 0.10000009 | H57: 1 | I57: =J57*$C$32 -> 202.85217 | J57: =(F57*G57*H57)/$C$32 -> 0.28978882
B58: =B57+1 -> 22 | C58: Natasha Mohunlal | F58: ='Work Component Split'!F43 -> 2943 | G58: ='Work Component Split'!K43 -> 0.1 | H58: 1 | I58: =J58*$C$32 -> 294.3 | J58: =(F58*G58*H58)/$C$32 -> 0.42042857
B59: =B58+1 -> 23 | C59: Swiiff | F59: ='Work Component Split'!F44 -> 2272.7 | G59: ='Work Component Split'!K44 -> 0.080991581 | H59: 1 | I59: =J59*$C$32 -> 184.06957 | J59: =(F59*G59*H59)/$C$32 -> 0.26295652
B60: =B59+1 -> 24 | C60: MMFS | F60: ='Work Component Split'!F47 -> 2916 | G60: ='Work Component Split'!K47 -> 0.1 | H60: 1 | I60: =J60*$C$32 -> 291.6 | J60: =(F60*G60*H60)/$C$32 -> 0.41657143
B61: =B60+1 -> 25 | C61: Bona By Wenzy | F61: ='Work Component Split'!F48 -> 4180 | G61: ='Work Component Split'!K48 -> 0.090430622 | H61: 1 | I61: =J61*$C$32 -> 378 | J61: =(F61*G61*H61)/$C$32 -> 0.54
B62: =B61+1 -> 26 | C62: Recovery Advisors | F62: ='Work Component Split'!F49 -> 1890 | G62: ='Work Component Split'!K49 -> 0.1 | H62: 1 | I62: =J62*$C$32 -> 189 | J62: =(F62*G62*H62)/$C$32 -> 0.27
B63: =B62+1 -> 27 | C63: Subtream | F63: ='Work Component Split'!F50 -> 2430 | G63: ='Work Component Split'!K50 -> 0.1 | H63: 1 | I63: =J63*$C$32 -> 243 | J63: =(F63*G63*H63)/$C$32 -> 0.34714286
B64: =B63+1 -> 28 | C64: Plush Spaces | F64: ='Work Component Split'!F51 -> 5352.48 | G64: ='Work Component Split'!K51 -> 0.1 | H64: 1 | I64: =J64*$C$32 -> 535.248 | J64: =(F64*G64*H64)/$C$32 -> 0.76464
B65: =B64+1 -> 29 | C65: CM Freelancing (Pty) Ltd | F65: ='Work Component Split'!F52 -> 2303.5043 | G65: ='Work Component Split'!K52 -> 0.083394677 | H65: 1 | I65: =J65*$C$32 -> 192.1 | J65: =(F65*G65*H65)/$C$32 -> 0.27442857
B66: =B65+1 -> 30 | C66: EKSN ENGINEERING | F66: ='Work Component Split'!F53 -> 3237.3 | G66: ='Work Component Split'!K53 -> 0.10000015 | H66: 1 | I66: =J66*$C$32 -> 323.73047 | J66: =(F66*G66*H66)/$C$32 -> 0.4624721
B67: =B66+1 -> 31 | C67: CN Freight | F67: ='Work Component Split'!F54 -> 1784.59 | G67: ='Work Component Split'!K54 -> 0.10000011 | H67: 1 | I67: =J67*$C$32 -> 178.4592 | J67: =(F67*G67*H67)/$C$32 -> 0.25494171
B68: =B67+1 -> 32 | C68: Khayelihle Properties | F68: ='Work Component Split'!F55 -> 4094.1 | G68: ='Work Component Split'!K55 -> 0.088318312 | H68: 1 | I68: =J68*$C$32 -> 361.584 | J68: =(F68*G68*H68)/$C$32 -> 0.51654857
B69: =B68+1 -> 33 | C69: Ndana Investments | F69: ='Work Component Split'!F56 -> 3240 | G69: ='Work Component Split'!K56 -> 0.1 | H69: 1 | I69: =J69*$C$32 -> 324 | J69: =(F69*G69*H69)/$C$32 -> 0.46285714
B70: =B69+1 -> 34 | C70: Primetyme | F70: ='Work Component Split'!F57 -> 1674 | G70: ='Work Component Split'!K57 -> 0.1 | H70: 1 | I70: =J70*$C$32 -> 167.4 | J70: =(F70*G70*H70)/$C$32 -> 0.23914286
B71: =B70+1 -> 35 | C71: SRYC | F71: ='Work Component Split'!F58 -> 2646 | G71: ='Work Component Split'!K58 -> 0.1 | H71: 1 | I71: =J71*$C$32 -> 264.6 | J71: =(F71*G71*H71)/$C$32 -> 0.378
... B73: =B72+1 -> 37 | C73: JFM Private property | F73: ='Work Component Split'!F60 -> 1069.2 | G73: ='Work Component Split'!K60 -> 0.1 | H73: 1 | I73: =J73*$C$32 -> 106.92 | J73: =(F73*G73*H73)/$C$32 -> 0.15274286
C76: Once Off Clients:
B77: 1 | C77: Aquity Innovations NPC | D77: Audit | H77: 1 | I77: =J77*$C$32 -> 0 | J77: =(F78*G78*H77)/$C$32 -> 0
B78: 2 | C78: Customers Appreciate Better Service (PTY) LTD | D78: AFS Preparation | H78: 1 | I78: =J78*$C$32 -> 0 | J78: =(F79*G79*H78)/$C$32 -> 0
B79: 3 | C79: DAWN RISK MANAGING AGENCY (PTY) LTD | D79: Auditors Letters review | H79: 1 | I79: =J79*$C$32 -> 0 | J79: =(F80*G80*H79)/$C$32 -> 0
B80: 4 | C80: Directec Consulting (Pty) Ltd | D80: Review Directors Income confirmation letter. | H80: 1 | I80: =J80*$C$32 -> 0 | J80: =(F81*G81*H80)/$C$32 -> 0
B81: 5 | C81: Portia | D81: Audit - Review of the reports and supporting documents. | H81: 1 | I81: =J81*$C$32 -> 0 | J81: =(F82*G82*H81)/$C$32 -> 0
B82: 6 | C82: Sefton Engineering (Pty) Ltd | D82: Review of AFS. | H82: 1 | I82: =J82*$C$32 -> 0 | J82: =(F83*G83*H82)/$C$32 -> 0
B83: 7 | C83: Simbarashe Makwembere | D83: SARS letter review | H83: 1 | I83: =J83*$C$32 -> 0 | J83: =(F84*G84*H83)/$C$32 -> 0
B84: 8 | H84: 1 | I84: =J84*$C$32 -> 0 | J84: =(F85*G85*H84)/$C$32 -> 0
B85: 9 | H85: 1 | I85: =J85*$C$32 -> 0 | J85: =(F86*G86*H85)/$C$32 -> 0
B86: 10 | H86: 1 | I86: =J86*$C$32 -> 0 | J86: =(F87*G87*H86)/$C$32 -> 0
F88: =SUM(F37:F87) -> 153817.62 | I88: =SUM(I35:I87) -> 14272.261 | J88: =SUM(J34:J87) -> 20.388944
E89: Excl VAT | F89: =100/115*F88 -> 133754.45 | H89: Excl VAT | I89: =100/115*I88 -> 12410.662
C95: Workflow Schedule for | E95: February | J95: 2026
C96: Charge Rate: | D96: Working Days in Month | F96: KPI % | G96: Hours per Day | H96: Monthly Budgeted Hours | I96: Total Scheduled Fees | J96: Hours Left
C97: =C32 -> 700 | D97: 20 | F97: =F32 -> 0.8 | G97: =G32 -> 8 | H97: =D97*G97*F97 -> 128 | I97: =I174 -> 24230.659 | J97: =H97-J174 -> 93.384773
C98: Entity Group \ Job Name | D98: Notes | F98: Estimated Fees for Job | G98: Team Members Job Completion % | H98: Pricing or Efficiency Override | I98: Budgeted WIP | J98: Job Budgeted Hrs | K98: Submission Date to client | L98: Accountants commnent on Due Date
C100: Monthly Recurring Work
C101: Management Accounts:
B102: 1 | C102: Maxopani Holdings | F102: 23085.91 | G102: 0.070059673 | H102: 1 | I102: =J102*$C$32 -> 1617.3913 | J102: =(F102*G102*H102)/$C$32 -> 2.310559
B103: 2 | C103: Sinet Africa | F103: 4320 | G103: 0.1 | H103: 1 | I103: =J103*$C$32 -> 432 | J103: =(F103*G103*H103)/$C$32 -> 0.61714286
B104: 3 | C104: Innovateher | F104: 24734.36 | G104: 0.099999989 | H104: 1 | I104: =J104*$C$32 -> 2473.4357 | J104: =(F104*G104*H104)/$C$32 -> 3.5334796
B105: 4 | C105: Khulio Electric | F105: 12960 | G105: 0.1 | H105: 1 | I105: =J105*$C$32 -> 1296 | J105: =(F105*G105*H105)/$C$32 -> 1.8514286
B106: 5 | C106: Hambo Lwethu | F106: 4610.52 | G106: 0.1 | H106: 1 | I106: =J106*$C$32 -> 461.052 | J106: =(F106*G106*H106)/$C$32 -> 0.65864571
B107: 6 | C107: Spade | F107: 0 | G107: 0 | H107: 1 | I107: =J107*$C$32 -> 0 | J107: =(F107*G107*H107)/$C$32 -> 0
B108: 7 | C108: Makhubela Incorporated | F108: 2045.02 | G108: 0.078739317 | H108: 1 | I108: =J108*$C$32 -> 161.02348 | J108: =(F108*G108*H108)/$C$32 -> 0.23003354
B109: 8 | C109: Destiny Finance (Pty) Ltd | F109: 8868.51 | G109: 0.064847421 | H109: 1 | I109: =J109*$C$32 -> 575.1 | J109: =(F109*G109*H109)/$C$32 -> 0.82157143
B110: 9 | C110: DR WW NGWATA PRACTICE INC | F110: 3173.06 | G110: 0.0873939 | H110: 1 | I110: =J110*$C$32 -> 277.30609 | J110: =(F110*G110*H110)/$C$32 -> 0.39615155
B111: 10 | C111: Bixa Consulting | F111: 2864.78 | G111: 0.084823267 | H111: 1 | I111: =J111*$C$32 -> 243 | J111: =(F111*G111*H111)/$C$32 -> 0.34714286
B112: 11 | C112: Mvundlane | F112: 2700 | G112: 0.1 | H112: 1 | I112: =J112*$C$32 -> 270 | J112: =(F112*G112*H112)/$C$32 -> 0.38571429
B113: 12 | C113: Solid Re Global | F113: 2535.65 | G113: 0.10000009 | H113: 1 | I113: =J113*$C$32 -> 253.56522 | J113: =(F113*G113*H113)/$C$32 -> 0.36223602
... B150: 49 | C150: JFM Private property | F150: 1069.2 | G150: 0.1 | H150: 1 | I150: =J150*$C$32 -> 106.92 | J150: =(F150*G150*H150)/$C$32 -> 0.15274286
C154: Once Off work:
B155: 1 | H155: 1 | I155: =J155*$C$32 -> 0 | J155: =(F155*G155*H155)/$C$32 -> 0
B156: 2 | H156: 1 | I156: =J156*$C$32 -> 0 | J156: =(F156*G156*H156)/$C$32 -> 0
B157: 3 | H157: 1 | I157: =J157*$C$32 -> 0 | J157: =(F157*G157*H157)/$C$32 -> 0
B158: 4 | H158: 1 | I158: =J158*$C$32 -> 0 | J158: =(F158*G158*H158)/$C$32 -> 0
B159: 5 | H159: 1 | I159: =J159*$C$32 -> 0 | J159: =(F159*G159*H159)/$C$32 -> 0
B160: 7 | H160: 1 | I160: =J160*$C$32 -> 0 | J160: =(F160*G160*H160)/$C$32 -> 0
B161: 8 | H161: 1 | I161: =J161*$C$32 -> 0 | J161: =(F161*G161*H161)/$C$32 -> 0
B162: 9 | H162: 1 | I162: =J162*$C$32 -> 0 | J162: =(F162*G162*H162)/$C$32 -> 0
B163: 10 | H163: 1 | I163: =J163*$C$32 -> 0 | J163: =(F163*G163*H163)/$C$32 -> 0
B164: 11 | H164: 1
...

Sheet Kenneth Jan - Dec '26
F3: Workflow Scheduling
B8: "A business is a commercial profitable enterprise that runs without you"
C10: Workflow Dashboard
B11: Senior Client Manager In Charge : | G11: Star Bongowongo
B12: Team Name: | G12: Kenneth Mashava
B14: Team Member: | D14: Kenneth | G14: Role: | J14: Accountant
C15: Analysis: | E15: Fees: | G15: Analysis: | K15: Hours:
C16: Annual Fee Budget | E16: =54720*12 -> 656640 | G16: Annual Budgeted Hours | K16: =E16/C32 -> 1459.2
C17: Scheduled Work and Jobs | E17: =+I67+I113+I182+I252+I322+I392+I462+I532+I602+I672+I742+I812 -> 45252.148 | G17: Scheduled Hours | K17: =+J67+J113+J182+J252+J322+J392+J462+J532+J602+J672+J742+J812 -> 100.56033
C18: Over (Under) Scheduled Work | E18: =E17-E16 -> -611387.85 | G18: Over (Under) Scheduled Work | K18: =K17-K16 -> -1358.6397
B20: Remaining Hours to Fill:
D21: January | E21: =J32 -> 58.501637 | F21: Apr | G21: =+J190 -> 121.6 | H21: July | I21: =+J400 -> 134.4 | J21: Oct | K21: =+J610 -> 147.2
D22: Feb | E22: =+J76 -> 103.33803 | F22: May | G22: =+J260 -> 140.8 | H22: Aug | I22: =J470 -> 134.4 | J22: Nov | K22: =+J680 -> 128
D23: Mar | E23: =+J121 -> 134.4 | F23: June | G23: =+J330 -> 128 | H23: Sept | I23: =+J540 -> 134.4 | J23: Dec | K23: =+J750 -> 128
B25: Total Productivity Hours To Fill : | G25: =SUM(E21:E23)+SUM(G21:G23)+SUM(I21:I23)+SUM(K21:K23) -> 1493.0397
C30: Workflow Schedule for | E30: January | J30: 2026
C31: Charge Rate: | D31: Working Days in Month | F31: KPI % | G31: Hours per Day | H31: Monthly Budgeted Hours | I31: Total Scheduled Fees | J31: Hours Left
C32: 450 | D32: 21 | F32: 0.8 | G32: 8 | H32: =D32*G32*F32 -> 134.4 | I32: =I67 -> 34154.263 | J32: =H32-J67 -> 58.501637
C33: Entity Group \ Job Name | D33: Notes | F33: Estimated Fees for Job | G33: Team Members Job Completion % | H33: Pricing or Efficiency Override | I33: Budgeted WIP | J33: Job Budgeted Hrs | K33: Submission Date to client | L33: Accountants commnent on Due Date
C35: Monthly Recurring Work
C36: Management Accounts:
B37: 1 | C37: Makhubela Incorporated | F37: ='Work Component Split'!F16 -> 2045.02 | G37: ='Work Component Split'!J16 -> 0.31495727 | H37: 1 | I37: =J37*$C$32 -> 644.09391 | J37: =(F37*G37*H37)/$C$32 -> 1.4313198
B38: 2 | C38: Destiny Finance (Pty) Ltd | F38: ='Work Component Split'!F17 -> 8868.51 | G38: ='Work Component Split'!J17 -> 0.25938968 | H38: 1 | I38: =J38*$C$32 -> 2300.4 | J38: =(F38*G38*H38)/$C$32 -> 5.112
B39: 3 | C39: DR WW NGWATA PRACTICE INC | F39: ='Work Component Split'!F18 -> 3173.06 | G39: ='Work Component Split'!J18 -> 0.3495756 | H39: 1 | I39: =J39*$C$32 -> 1109.2243 | J39: =(F39*G39*H39)/$C$32 -> 2.464943
B40: 4 | C40: Bixa Consulting | F40: ='Work Component Split'!F19 -> 2864.78 | G40: ='Work Component Split'!J19 -> 0.33929307 | H40: 1 | I40: =J40*$C$32 -> 972 | J40: =(F40*G40*H40)/$C$32 -> 2.16
B41: 5 | C41: Mvundlane | F41: ='Work Component Split'!F20 -> 2700 | G41: ='Work Component Split'!J20 -> 0.4 | H41: 1 | I41: =J41*$C$32 -> 1080 | J41: =(F41*G41*H41)/$C$32 -> 2.4
B42: 6 | C42: Solid Re Global | F42: ='Work Component Split'!F21 -> 2535.65 | G42: ='Work Component Split'!J21 -> 0.40000034 | H42: 1 | I42: =J42*$C$32 -> 1014.2609 | J42: =(F42*G42*H42)/$C$32 -> 2.253913
B43: 7 | C43: Drs Koranteng | F43: ='Work Component Split'!F22 -> 2652.29 | G43: ='Work Component Split'!J22 -> 0.40000085 | H43: 1 | I43: =J43*$C$32 -> 1060.9183 | J43: =(F43*G43*H43)/$C$32 -> 2.3575961
B44: 8 | C44: Destiny Portfolio | F44: ='Work Component Split'!F23 -> 3868.56 | G44: ='Work Component Split'!J23 -> 0.39999964 | H44: 1 | I44: =J44*$C$32 -> 1547.4226 | J44: =(F44*G44*H44)/$C$32 -> 3.4387169
B45: 9 | C45: Astra Matellite | F45: ='Work Component Split'!F27 -> 5328.2935 | G45: ='Work Component Split'!J27 -> 0.25703637 | H45: 1 | I45: =J45*$C$32 -> 1369.5652 | J45: =(F45*G45*H45)/$C$32 -> 3.0434783
C48: Once Off work:
B49: 1 | C49: Siyaphila Trading | F49: 41391.31 | G49: 0.4 | H49: 1 | I49: =J49*$C$32 -> 16556.524 | J49: =(F49*G49*H49)/$C$32 -> 36.792276
B50: 2 | C50: Astra Matellite | F50: 7222.06 | G50: 0.9 | H50: 1 | I50: =J50*$C$32 -> 6499.854 | J50: =(F50*G50*H50)/$C$32 -> 14.44412
B51: 4 | H51: 1 | I51: =J51*$C$32 -> 0 | J51: =(F51*G51*H51)/$C$32 -> 0
B52: 5 | H52: 1 | I52: =J52*$C$32 -> 0 | J52: =(F52*G52*H52)/$C$32 -> 0
B53: 6 | H53: 1 | I53: =J53*$C$32 -> 0 | J53: =(F53*G53*H53)/$C$32 -> 0
B54: 7 | H54: 1 | I54: =J54*$C$32 -> 0 | J54: =(F54*G54*H54)/$C$32 -> 0
B55: 8 | H55: 1 | I55: =J55*$C$32 -> 0 | J55: =(F55*G55*H55)/$C$32 -> 0
B56: 9 | H56: 1 | I56: =J56*$C$32 -> 0 | J56: =(F56*G56*H56)/$C$32 -> 0
B57: 10 | H57: 1 | I57: =J57*$C$32 -> 0 | J57: =(F57*G57*H57)/$C$32 -> 0
B58: 11 | H58: 1 | I58: =J58*$C$32 -> 0 | J58: =(F58*G58*H58)/$C$32 -> 0
B59: 12 | H59: 1 | I59: =J59*$C$32 -> 0 | J59: =(F59*G59*H59)/$C$32 -> 0
B60: 13 | H60: 1 | I60: =J60*$C$32 -> 0 | J60: =(F60*G60*H60)/$C$32 -> 0
B61: 14 | H61: 1 | I61: =J61*$C$32 -> 0 | J61: =(F61*G61*H61)/$C$32 -> 0
B62: 16 | H62: 1 | I62: =J62*$C$32 -> 0 | J62: =(F62*G62*H62)/$C$32 -> 0
... B65: 20 | H65: 1 | I65: =J65*$C$32 -> 0 | J65: =(F65*G65*H65)/$C$32 -> 0
F67: =SUM(F37:F66) -> 82649.533 | I67: =SUM(I35:I66) -> 34154.263 | J67: =SUM(J34:J66) -> 75.898363
E68: Excl VAT | F68: =100/115*F67 -> 71869.16 | H68: Excl VAT | I68: =100/115*I67 -> 29699.359
C74: Workflow Schedule for | E74: February | J74: 2026
C75: Charge Rate: | D75: Working Days in Month | F75: KPI % | G75: Hours per Day | H75: Monthly Budgeted Hours | I75: Total Scheduled Fees | J75: Hours Left
C76: =C32 -> 450 | D76: 20 | F76: =F32 -> 0.8 | G76: =G32 -> 8 | H76: =D76*G76*F76 -> 128 | I76: =I113 -> 11097.885 | J76: =H76-J113 -> 103.33803
C77: Entity Group \ Job Name | D77: Notes | F77: Estimated Fees for Job | G77: Team Members Job Completion % | H77: Pricing or Efficiency Override | I77: Budgeted WIP | J77: Job Budgeted Hrs | K77: Submission Date to client | L77: Accountants commnent on Due Date
C79: Monthly Recurring Work
C80: Management Accounts:
B81: 1 | C81: Makhubela Incorporated | F81: 2045.02 | G81: 0.31495727 | H81: 1 | I81: =J81*$C$32 -> 644.09391 | J81: =(F81*G81*H81)/$C$32 -> 1.4313198
B82: 2 | C82: Destiny Finance (Pty) Ltd | F82: 8868.51 | G82: 0.25938968 | H82: 1 | I82: =J82*$C$32 -> 2300.4 | J82: =(F82*G82*H82)/$C$32 -> 5.112
B83: 3 | C83: DR WW NGWATA PRACTICE INC | F83: 3173.06 | G83: 0.3495756 | H83: 1 | I83: =J83*$C$32 -> 1109.2243 | J83: =(F83*G83*H83)/$C$32 -> 2.464943
B84: 4 | C84: Bixa Consulting | F84: 2864.78 | G84: 0.33929307 | H84: 1 | I84: =J84*$C$32 -> 972 | J84: =(F84*G84*H84)/$C$32 -> 2.16
B85: 5 | C85: Mvundlane | F85: 2700 | G85: 0.4 | H85: 1 | I85: =J85*$C$32 -> 1080 | J85: =(F85*G85*H85)/$C$32 -> 2.4
B86: 6 | C86: Solid Re Global | F86: 2535.65 | G86: 0.40000034 | H86: 1 | I86: =J86*$C$32 -> 1014.2609 | J86: =(F86*G86*H86)/$C$32 -> 2.253913
B87: 7 | C87: Drs Koranteng | F87: 2652.29 | G87: 0.40000085 | H87: 1 | I87: =J87*$C$32 -> 1060.9183 | J87: =(F87*G87*H87)/$C$32 -> 2.3575961
B88: 8 | C88: Destiny Portfolio | F88: 3868.56 | G88: 0.39999964 | H88: 1 | I88: =J88*$C$32 -> 1547.4226 | J88: =(F88*G88*H88)/$C$32 -> 3.4387169
B89: 9 | C89: Astra Matellite | F89: 5328.2935 | G89: 0.25703637 | H89: 1 | I89: =J89*$C$32 -> 1369.5652 | J89: =(F89*G89*H89)/$C$32 -> 3.0434783
B90: 10 | H90: 1 | I90: =J90*$C$32 -> 0 | J90: =(F90*G90*H90)/$C$32 -> 0
C93: Once Off work:
B94: 1 | H94: 1 | I94: =J94*$C$32 -> 0 | J94: =(F94*G94*H94)/$C$32 -> 0
B95: 2 | H95: 1 | I95: =J95*$C$32 -> 0 | J95: =(F95*G95*H95)/$C$32 -> 0
B96: 3 | H96: 1 | I96: =J96*$C$32 -> 0 | J96: =(F96*G96*H96)/$C$32 -> 0
B97: 4 | H97: 1 | I97: =J97*$C$32 -> 0 | J97: =(F97*G97*H97)/$C$32 -> 0
B98: 5 | H98: 1 | I98: =J98*$C$32 -> 0 | J98: =(F98*G98*H98)/$C$32 -> 0
B99: 7 | H99: 1 | I99: =J99*$C$32 -> 0 | J99: =(F99*G99*H99)/$C$32 -> 0
B100: 8 | H100: 1 | I100: =J100*$C$32 -> 0 | J100: =(F100*G100*H100)/$C$32 -> 0
B101: 9 | H101: 1 | I101: =J101*$C$32 -> 0 | J101: =(F101*G101*H101)/$C$32 -> 0
B102: 10 | H102: 1 | I102: =J102*$C$32 -> 0 | J102: =(F102*G102*H102)/$C$32 -> 0
B103: 11 | H103: 1
B104: 12 | H104: 1
B105: 14 | H105: 1 | I105: =J105*$C$32 -> 0 | J105: =(F105*G105*H105)/$C$32 -> 0
B106: 15 | H106: 1 | I106: =J106*$C$32 -> 0 | J106: =(F106*G106*H106)/$C$32 -> 0
B107: 16 | H107: 1 | I107: =J107*$C$32 -> 0 | J107: =(F107*G107*H107)/$C$32 -> 0
B108: 17 | H108: 1 | I108: =J108*$C$32 -> 0 | J108: =(F108*G108*H108)/$C$32 -> 0
B109: 18 | H109: 1 | I109: =J109*$C$32 -> 0 | J109: =(F109*G109*H109)/$C$32 -> 0
B110: 19 | H110: 1 | I110: =J110*$C$32 -> 0 | J110: =(F110*G110*H110)/$C$32 -> 0
B111: 20 | H111: 1 | I111: =J111*$C$32 -> 0 | J111: =(F111*G111*H111)/$C$32 -> 0
F113: =SUM(F79:F112) -> 34036.163 | I113: =SUM(I81:I112) -> 11097.885 | J113: =SUM(J78:J112) -> 24.661967
E114: Excl VAT | F114: =100/115*F113 -> 29596.664 | H114: Excl VAT | I114: =100/115*I113 -> 9650.335
C119: Workflow Schedule for | E119: March | J119: 2026
C120: Charge Rate: | D120: Working Days in Month | F120: KPI % | G120: Hours per Day | H120: Monthly Budgeted Hours | I120: Total Scheduled Fees | J120: Hours Left
C121: =C76 -> 450 | D121: 21 | F121: =F76 -> 0.8 | G121: =G76 -> 8 | H121: =D121*G121*F121 -> 134.4 | I121: =I182 -> 0 | J121: =H121-J182 -> 134.4
C122: Entity Group \ Job Name | D122: Notes | F122: Estimated Fees for Job | G122: Team Members Job Completion % | H122: Pricing or Efficiency Override | I122: Budgeted WIP | J122: Job Budgeted Hrs | K122: Submission Date to client | L122: Accountants commnent on Due Date
C124: Monthly Recurring Work
C125: Mamangement Accounts:
B126: 1 | H126: 1 | I126: =J126*$C$32 -> 0 | J126: =(F126*G126*H126)/$C$32 -> 0
B127: 2 | H127: 1 | I127: =J127*$C$32 -> 0 | J127: =(F127*G127*H127)/$C$32 -> 0
B128: 3 | H128: 1 | I128: =J128*$C$32 -> 0 | J128: =(F128*G128*H128)/$C$32 -> 0
B129: 4 | H129: 1 | I129: =J129*$C$32 -> 0 | J129: =(F129*G129*H129)/$C$32 -> 0
B130: 5 | H130: 1 | I130: =J130*$C$32 -> 0 | J130: =(F130*G130*H130)/$C$32 -> 0
B131: 6 | H131: 1 | I131: =J131*$C$32 -> 0 | J131: =(F131*G131*H131)/$C$32 -> 0
B132: 7 | H132: 1 | I132: =J132*$C$32 -> 0 | J132: =(F132*G132*H132)/$C$32 -> 0
B133: 8 | H133: 1 | I133: =J133*$C$32 -> 0 | J133: =(F133*G133*H133)/$C$32 -> 0
B134: 9 | H134: 1 | I134: =J134*$C$32 -> 0 | J134: =(F134*G134*H134)/$C$32 -> 0
...

Sheet Tatenda Jan - Dec '26
F3: Workflow Scheduling
B8: "A business is a commercial profitable enterprise that runs without you"
C10: Workflow Dashboard
B11: Senior Client Manager In Charge : | G11: Star Bongowongo
B12: Team Name: | G12: Tatenda Chasakara
B14: Team Member: | D14: Tatenda | G14: Role: | J14: Accountant
C15: Analysis: | E15: Fees: | G15: Analysis: | K15: Hours:
C16: Annual Fee Budget | E16: =54720*12 -> 656640 | G16: Annual Budgeted Hours | K16: =E16/C32 -> 1459.2
C17: Scheduled Work and Jobs | E17: =+I56+I102+I171+I241+I311+I381+I451+I521+I591+I661+I731+I801 -> 35013.261 | G17: Scheduled Hours | K17: =+J56+J102+J171+J241+J311+J381+J451+J521+J591+J661+J731+J801 -> 77.807247
C18: Over (Under) Scheduled Work | E18: =E17-E16 -> -621626.74 | G18: Over (Under) Scheduled Work | K18: =K17-K16 -> -1381.3928
B20: Remaining Hours to Fill:
D21: January | E21: =J32 -> 112.4139 | F21: Apr | G21: =+J179 -> 121.6 | H21: July | I21: =+J389 -> 134.4 | J21: Oct | K21: =+J599 -> 147.2
D22: Feb | E22: =+J65 -> 72.178851 | F22: May | G22: =+J249 -> 140.8 | H22: Aug | I22: =J459 -> 134.4 | J22: Nov | K22: =+J669 -> 128
D23: Mar | E23: =+J110 -> 134.4 | F23: June | G23: =+J319 -> 128 | H23: Sept | I23: =+J529 -> 134.4 | J23: Dec | K23: =+J739 -> 128
B25: Total Productivity Hours To Fill : | G25: =SUM(E21:E23)+SUM(G21:G23)+SUM(I21:I23)+SUM(K21:K23) -> 1515.7928
C30: Workflow Schedule for | E30: January | J30: 2026
C31: Charge Rate: | D31: Working Days in Month | F31: KPI % | G31: Hours per Day | H31: Monthly Budgeted Hours | I31: Total Scheduled Fees | J31: Hours Left
C32: 450 | D32: 21 | F32: 0.8 | G32: 8 | H32: =D32*G32*F32 -> 134.4 | I32: =I56 -> 9893.744 | J32: =H32-J56 -> 112.4139
C33: Entity Group \ Job Name | D33: Notes | F33: Estimated Fees for Job | G33: Team Members Job Completion % | H33: Pricing or Efficiency Override | I33: Budgeted WIP | J33: Job Budgeted Hrs | K33: Submission Date to client | L33: Accountants commnent on Due Date
C35: Monthly Recurring Work
C36: Management Accounts:
B37: 1 | C37: Innovateher | F37: ='Work Component Split'!F12 -> 24734.36 | G37: ='Work Component Split'!J11 -> 0.4 | H37: 1 | I37: =J37*$C$32 -> 9893.744 | J37: =(F37*G37*H37)/$C$32 -> 21.986098
C40: Once Off Client:
B41: 1 | C41: Aquity Innovations NPC | D41: Audit | H41: 1 | I41: =J41*$C$32 -> 0 | J41: =(F41*G41*H41)/$C$32 -> 0
B42: 2 | C42: Hambo Lwethu Travel | D42: Bank Reconciliation | H42: 1 | I42: =J42*$C$32 -> 0 | J42: =(F42*G42*H42)/$C$32 -> 0
B43: 4 | C43: Implantcast SA (Pty) Ltd | D43: Audit | H43: 1 | I43: =J43*$C$32 -> 0 | J43: =(F43*G43*H43)/$C$32 -> 0
B44: 7 | C44: Rutendo Addeline Gavhera | D44: Tax submission | H44: 1 | I44: =J44*$C$32 -> 0 | J44: =(F44*G44*H44)/$C$32 -> 0
B45: 8 | C45: SA SELLO | D45: Tax submission | H45: 1 | I45: =J45*$C$32 -> 0 | J45: =(F45*G45*H45)/$C$32 -> 0
B46: 9 | C46: Spade Encryption (Pty) Ltd | D46: Tax submission | H46: 1 | I46: =J46*$C$32 -> 0 | J46: =(F46*G46*H46)/$C$32 -> 0
B47: 11 | H47: 1 | I47: =J47*$C$32 -> 0 | J47: =(F47*G47*H47)/$C$32 -> 0
B48: 12 | H48: 1 | I48: =J48*$C$32 -> 0 | J48: =(F48*G48*H48)/$C$32 -> 0
B49: 13 | H49: 1 | I49: =J49*$C$32 -> 0 | J49: =(F49*G49*H49)/$C$32 -> 0
B50: 14 | H50: 1 | I50: =J50*$C$32 -> 0 | J50: =(F50*G50*H50)/$C$32 -> 0
B51: 16 | H51: 1 | I51: =J51*$C$32 -> 0 | J51: =(F51*G51*H51)/$C$32 -> 0
B52: 17 | H52: 1 | I52: =J52*$C$32 -> 0 | J52: =(F52*G52*H52)/$C$32 -> 0
B53: 19 | H53: 1 | I53: =J53*$C$32 -> 0 | J53: =(F53*G53*H53)/$C$32 -> 0
B54: 20 | H54: 1 | I54: =J54*$C$32 -> 0 | J54: =(F54*G54*H54)/$C$32 -> 0
F56: =SUM(F37:F55) -> 24734.36 | I56: =SUM(I35:I55) -> 9893.744 | J56: =SUM(J34:J55) -> 21.986098
E57: Excl VAT | F57: =100/115*F56 -> 21508.139 | H57: Excl VAT | I57: =100/115*I56 -> 8603.2557
C63: Workflow Schedule for | E63: February | J63: 2026
C64: Charge Rate: | D64: Working Days in Month | F64: KPI % | G64: Hours per Day | H64: Monthly Budgeted Hours | I64: Total Scheduled Fees | J64: Hours Left
C65: =C32 -> 450 | D65: 20 | F65: =F32 -> 0.8 | G65: =G32 -> 8 | H65: =D65*G65*F65 -> 128 | I65: =I102 -> 25119.517 | J65: =H65-J102 -> 72.178851
C66: Entity Group \ Job Name | D66: Notes | F66: Estimated Fees for Job | G66: Team Members Job Completion % | H66: Pricing or Efficiency Override | I66: Budgeted WIP | J66: Job Budgeted Hrs | K66: Submission Date to client | L66: Accountants commnent on Due Date
C68: Monthly Recurring Work
C69: Management Accounts:
B70: 1 | C70: Khulio Electric | F70: 12960 | G70: 0.4 | H70: 1 | I70: =J70*$C$32 -> 5184 | J70: =(F70*G70*H70)/$C$32 -> 11.52
B71: 2 | C71: Innovateher | F71: 24734.36 | G71: 0.4 | H71: 1 | I71: =J71*$C$32 -> 9893.744 | J71: =(F71*G71*H71)/$C$32 -> 21.986098
B72: 3 | C72: Hambo Lwethu | F72: 4610.52 | G72: 0.4 | H72: 1 | I72: =J72*$C$32 -> 1844.208 | J72: =(F72*G72*H72)/$C$32 -> 4.09824
A73: - | B73: 4 | C73: Spade - New client | F73: 0 | G73: 0 | H73: 1 | I73: =J73*$C$32 -> 0 | J73: =(F73*G73*H73)/$C$32 -> 0
B74: 5 | C74: Maxopani Holdings | F74: 23085.91 | G74: 0.28023869 | H74: 1 | I74: =J74*$C$32 -> 6469.5652 | J74: =(F74*G74*H74)/$C$32 -> 14.376812
B75: 6 | C75: Sinet | F75: 4320 | G75: 0.4 | H75: 1 | I75: =J75*$C$32 -> 1728 | J75: =(F75*G75*H75)/$C$32 -> 3.84
B76: 7 | H76: 1 | I76: =J76*$C$32 -> 0 | J76: =(F76*G76*H76)/$C$32 -> 0
B77: 8 | H77: 1 | I77: =J77*$C$32 -> 0 | J77: =(F77*G77*H77)/$C$32 -> 0
B78: 9 | H78: 1 | I78: =J78*$C$32 -> 0 | J78: =(F78*G78*H78)/$C$32 -> 0
B79: 10 | H79: 1 | I79: =J79*$C$32 -> 0 | J79: =(F79*G79*H79)/$C$32 -> 0
C82: Once Off work:
B83: 1 | H83: 1 | I83: =J83*$C$32 -> 0 | J83: =(F83*G83*H83)/$C$32 -> 0
B84: 2 | H84: 1 | I84: =J84*$C$32 -> 0 | J84: =(F84*G84*H84)/$C$32 -> 0
B85: 3 | H85: 1 | I85: =J85*$C$32 -> 0 | J85: =(F85*G85*H85)/$C$32 -> 0
B86: 4 | H86: 1 | I86: =J86*$C$32 -> 0 | J86: =(F86*G86*H86)/$C$32 -> 0
B87: 5 | H87: 1 | I87: =J87*$C$32 -> 0 | J87: =(F87*G87*H87)/$C$32 -> 0
B88: 7 | H88: 1 | I88: =J88*$C$32 -> 0 | J88: =(F88*G88*H88)/$C$32 -> 0
B89: 8 | H89: 1 | I89: =J89*$C$32 -> 0 | J89: =(F89*G89*H89)/$C$32 -> 0
B90: 9 | H90: 1 | I90: =J90*$C$32 -> 0 | J90: =(F90*G90*H90)/$C$32 -> 0
B91: 10 | H91: 1 | I91: =J91*$C$32 -> 0 | J91: =(F91*G91*H91)/$C$32 -> 0
B92: 11 | H92: 1
B93: 12 | H93: 1
B94: 14 | H94: 1 | I94: =J94*$C$32 -> 0 | J94: =(F94*G94*H94)/$C$32 -> 0
B95: 15 | H95: 1 | I95: =J95*$C$32 -> 0 | J95: =(F95*G95*H95)/$C$32 -> 0
B96: 16 | H96: 1 | I96: =J96*$C$32 -> 0 | J96: =(F96*G96*H96)/$C$32 -> 0
B97: 17 | H97: 1 | I97: =J97*$C$32 -> 0 | J97: =(F97*G97*H97)/$C$32 -> 0
B98: 18 | H98: 1 | I98: =J98*$C$32 -> 0 | J98: =(F98*G98*H98)/$C$32 -> 0
B99: 19 | H99: 1 | I99: =J99*$C$32 -> 0 | J99: =(F99*G99*H99)/$C$32 -> 0
B100: 20 | H100: 1 | I100: =J100*$C$32 -> 0 | J100: =(F100*G100*H100)/$C$32 -> 0
F102: =SUM(F68:F101) -> 69710.79 | I102: =SUM(I70:I101) -> 25119.517 | J102: =SUM(J67:J101) -> 55.821149
E103: Excl VAT | F103: =100/115*F102 -> 60618.078 | H103: Excl VAT | I103: =100/115*I102 -> 21843.058
C108: Workflow Schedule for | E108: March | J108: 2026
C109: Charge Rate: | D109: Working Days in Month | F109: KPI % | G109: Hours per Day | H109: Monthly Budgeted Hours | I109: Total Scheduled Fees | J109: Hours Left
C110: =C65 -> 450 | D110: 21 | F110: =F65 -> 0.8 | G110: =G65 -> 8 | H110: =D110*G110*F110 -> 134.4 | I110: =I171 -> 0 | J110: =H110-J171 -> 134.4
C111: Entity Group \ Job Name | D111: Notes | F111: Estimated Fees for Job | G111: Team Members Job Completion % | H111: Pricing or Efficiency Override | I111: Budgeted WIP | J111: Job Budgeted Hrs | K111: Submission Date to client | L111: Accountants commnent on Due Date
C113: Monthly Recurring Work
C114: Mamangement Accounts:
B115: 1 | H115: 1 | I115: =J115*$C$32 -> 0 | J115: =(F115*G115*H115)/$C$32 -> 0
B116: 2 | H116: 1 | I116: =J116*$C$32 -> 0 | J116: =(F116*G116*H116)/$C$32 -> 0
B117: 3 | H117: 1 | I117: =J117*$C$32 -> 0 | J117: =(F117*G117*H117)/$C$32 -> 0
B118: 4 | H118: 1 | I118: =J118*$C$32 -> 0 | J118: =(F118*G118*H118)/$C$32 -> 0
B119: 5 | H119: 1 | I119: =J119*$C$32 -> 0 | J119: =(F119*G119*H119)/$C$32 -> 0
B120: 6 | H120: 1 | I120: =J120*$C$32 -> 0 | J120: =(F120*G120*H120)/$C$32 -> 0
B121: 7 | H121: 1 | I121: =J121*$C$32 -> 0 | J121: =(F121*G121*H121)/$C$32 -> 0
B122: 8 | H122: 1 | I122: =J122*$C$32 -> 0 | J122: =(F122*G122*H122)/$C$32 -> 0
B123: 9 | H123: 1 | I123: =J123*$C$32 -> 0 | J123: =(F123*G123*H123)/$C$32 -> 0
B124: 10 | H124: 1 | I124: =J124*$C$32 -> 0 | J124: =(F124*G124*H124)/$C$32 -> 0
H125: 1 | I125: =J125*$C$32 -> 0 | J125: =(F125*G125*H125)/$C$32 -> 0
C127: Payroll:
B128: 1 | H128: 1 | I128: =J128*$C$32 -> 0 | J128: =(F128*G128*H128)/$C$32 -> 0
B129: 2 | H129: 1 | I129: =J129*$C$32 -> 0 | J129: =(F129*G129*H129)/$C$32 -> 0
B130: 3 | H130: 1 | I130: =J130*$C$32 -> 0 | J130: =(F130*G130*H130)/$C$32 -> 0
B131: 5 | H131: 1 | I131: =J131*$C$32 -> 0 | J131: =(F131*G131*H131)/$C$32 -> 0
B132: 6 | H132: 1 | I132: =J132*$C$32 -> 0 | J132: =(F132*G132*H132)/$C$32 -> 0
B133: 7 | H133: 1 | I133: =J133*$C$32 -> 0 | J133: =(F133*G133*H133)/$C$32 -> 0
...

Sheet Rudzi Jan - Dec '26
F3: Workflow Scheduling
B8: "A business is a commercial profitable enterprise that runs without you"
C10: Workflow Dashboard
B11: Senior Client Manager In Charge : | G11: Star Bongowongo
B12: Team Name: | G12: Rudzi Mziki
B14: Team Member: | D14: Rudzi | G14: Role: | J14: Accounting Intern
C15: Analysis: | E15: Fees: | G15: Analysis: | K15: Hours:
C16: Annual Fee Budget | E16: =50512*12 -> 606144 | G16: Annual Budgeted Hours | K16: =E16/C32 -> 1346.9867
C17: Scheduled Work and Jobs | E17: =+I64+I108+I177+I247+I317+I387+I457+I527+I597+I667+I737+I807 -> 33101.377 | G17: Scheduled Hours | K17: =+J64+J108+J177+J247+J317+J387+J457+J527+J597+J667+J737+J807 -> 73.558615
C18: Over (Under) Scheduled Work | E18: =E17-E16 -> -573042.62 | G18: Over (Under) Scheduled Work | K18: =K17-K16 -> -1273.4281
B20: Remaining Hours to Fill:
D21: January | E21: =J32 -> 104.78245 | F21: Apr | G21: =+J185 -> 121.6 | H21: July | I21: =+J395 -> 134.4 | J21: Oct | K21: =+J605 -> 147.2
D22: Feb | E22: =+J73 -> 84.058938 | F22: May | G22: =+J255 -> 140.8 | H22: Aug | I22: =J465 -> 134.4 | J22: Nov | K22: =+J675 -> 128
D23: Mar | E23: =+J116 -> 134.4 | F23: June | G23: =+J325 -> 128 | H23: Sept | I23: =+J535 -> 134.4 | J23: Dec | K23: =+J745 -> 128
B25: Total Productivity Hours To Fill : | G25: =SUM(E21:E23)+SUM(G21:G23)+SUM(I21:I23)+SUM(K21:K23) -> 1520.0414
C30: Workflow Schedule for | E30: January | J30: 2026
C31: Charge Rate: | D31: Working Days in Month | F31: KPI % | G31: Hours per Day | H31: Monthly Budgeted Hours | I31: Total Scheduled Fees | J31: Hours Left
C32: 450 | D32: 21 | F32: 0.8 | G32: 8 | H32: =D32*G32*F32 -> 134.4 | I32: =I64 -> 13327.899 | J32: =H32-J64 -> 104.78245
C33: Entity Group \ Job Name | D33: Notes | F33: Estimated Fees for Job | G33: Team Members Job Completion % | H33: Pricing or Efficiency Override | I33: Budgeted WIP | J33: Job Budgeted Hrs | K33: Submission Date to client | L33: Accountants commnent on Due Date
C35: Monthly Recurring Work
C36: Management Accounts:
B37: 1 | C37: CREATIVE VALLEY NURSERY SCHOOL | F37: ='Work Component Split'!F29 -> 2994.59 | G37: ='Work Component Split'!J29 -> 0.27513672 | H37: 1 | I37: =J37*$C$32 -> 823.92167 | J37: =(F37*G37*H37)/$C$32 -> 1.830937
B38: 2 | C38: Rentals Proper team Fourways | F38: ='Work Component Split'!F34 -> 3423.13 | G38: ='Work Component Split'!J34 -> 0.40000005 | H38: 1 | I38: =J38*$C$32 -> 1369.2522 | J38: =(F38*G38*H38)/$C$32 -> 3.0427826
B39: 3 | C39: Mectech Motors | F39: ='Work Component Split'!F36 -> 6389.28 | G39: ='Work Component Split'!K36 -> 0.08296146 | H39: 1 | I39: =J39*$C$32 -> 530.064 | J39: =(F39*G39*H39)/$C$32 -> 1.17792
B40: 4 | C40: R Protections | F40: ='Work Component Split'!F39 -> 8100 | G40: ='Work Component Split'!J39 -> 0.4 | H40: 1 | I40: =J40*$C$32 -> 3240 | J40: =(F40*G40*H40)/$C$32 -> 7.2
B41: 5 | C41: TMM TECH | F41: ='Work Component Split'!F35 -> 3549.91 | G41: ='Work Component Split'!J35 -> 0.40000034 | H41: 1 | I41: =J41*$C$32 -> 1419.9652 | J41: =(F41*G41*H41)/$C$32 -> 3.1554783
B42: 6 | C42: Chemstrat | F42: ='Work Component Split'!F38 -> 14040 | G42: ='Work Component Split'!J38 -> 0.4 | H42: 1 | I42: =J42*$C$32 -> 5616 | J42: =(F42*G42*H42)/$C$32 -> 12.48
B43: 7 | C43: Blue Hills | F43: ='Work Component Split'!F37 -> 3895.65 | G43: ='Work Component Split'!K37 -> 0.084375047 | H43: 1 | I43: =J43*$C$32 -> 328.69565 | J43: =(F43*G43*H43)/$C$32 -> 0.73043478
C45: Once Off work:
B46: 1 | C46: Aquity Innovations NPC | D46: Audit | H46: 1 | I46: =J46*$C$32 -> 0 | J46: =(F46*G46*H46)/$C$32 -> 0
B47: 2 | C47: Bongani Buthelezi | D47: Prepare rental income schedule | H47: 1 | I47: =J47*$C$32 -> 0 | J47: =(F47*G47*H47)/$C$32 -> 0
B48: 4 | C48: Nosipho | D48: Bank statement requisition, cost estimation | H48: 1 | I48: =J48*$C$32 -> 0 | J48: =(F48*G48*H48)/$C$32 -> 0
B49: 5 | C49: DR P Ngwata | D49: due dilligene reports | H49: 1 | I49: =J49*$C$32 -> 0 | J49: =(F49*G49*H49)/$C$32 -> 0
B50: 6 | C50: EmpowerXX | D50: AFS Preparation | H50: 1 | I50: =J50*$C$32 -> 0 | J50: =(F50*G50*H50)/$C$32 -> 0
B51: 7 | C51: Freshly Ground (Pty) Ltd | D51: Management accounts Review | H51: 1 | I51: =J51*$C$32 -> 0 | J51: =(F51*G51*H51)/$C$32 -> 0
B52: 8 | C52: Giant Bee Logistics Pty Ltd | D52: SARS Dispute Resolution | H52: 1 | I52: =J52*$C$32 -> 0 | J52: =(F52*G52*H52)/$C$32 -> 0
B53: 9 | C53: Hylee Choto | D53: 2nd Provisional tax submission , ITR 14 - submission | H53: 1 | I53: =J53*$C$32 -> 0 | J53: =(F53*G53*H53)/$C$32 -> 0
B54: 10 | C54: Jacas Trading (Pty) Ltd | D54: Management accounts | H54: 1 | I54: =J54*$C$32 -> 0 | J54: =(F54*G54*H54)/$C$32 -> 0
B55: 11 | C55: KHANYA CONSORTIUM | D55: (1st) Provisional Tax Submission | H55: 1 | I55: =J55*$C$32 -> 0 | J55: =(F55*G55*H55)/$C$32 -> 0
B56: 12 | C56: Mosuhlamakwe Projects and Trading Enterprise (Pty) Ltd | D56: ITR 14 - submission | H56: 1 | I56: =J56*$C$32 -> 0 | J56: =(F56*G56*H56)/$C$32 -> 0
B57: 13 | C57: Nkothimemo2021 Trading (Pty) Ltd | D57: Transaction Allocations ,AFS Preparation , management accounts review | H57: 1 | I57: =J57*$C$32 -> 0 | J57: =(F57*G57*H57)/$C$32 -> 0
... B60: 17 | C60: Simbarashe Makwembere | D60: Consulting Services | H60: 1 | I60: =J60*$C$32 -> 0 | J60: =(F60*G60*H60)/$C$32 -> 0
B61: 19 | H61: 1 | I61: =J61*$C$32 -> 0 | J61: =(F61*G61*H61)/$C$32 -> 0
B62: 20 | H62: 1 | I62: =J62*$C$32 -> 0 | J62: =(F62*G62*H62)/$C$32 -> 0
F64: =SUM(F37:F63) -> 42392.56 | I64: =SUM(I35:I63) -> 13327.899 | J64: =SUM(J34:J63) -> 29.617553
E65: Excl VAT | F65: =100/115*F64 -> 36863.096 | H65: Excl VAT | I65: =100/115*I64 -> 11589.477
C71: Workflow Schedule for | E71: February | J71: 2026
C72: Charge Rate: | D72: Working Days in Month | F72: KPI % | G72: Hours per Day | H72: Monthly Budgeted Hours | I72: Total Scheduled Fees | J72: Hours Left
C73: 350 | D73: 20 | F73: =F32 -> 0.8 | G73: =G32 -> 8 | H73: =D73*G73*F73 -> 128 | I73: =I108 -> 19773.478 | J73: =H73-J108 -> 84.058938
C74: Entity Group \ Job Name | D74: Notes | F74: Estimated Fees for Job | G74: Team Members Job Completion % | H74: Pricing or Efficiency Override | I74: Budgeted WIP | J74: Job Budgeted Hrs | K74: Submission Date to client | L74: Accountants commnent on Due Date
C76: Monthly Recurring Work
C77: Management Accounts:
B78: 1 | C78: CREATIVE VALLEY NURSERY SCHOOL | F78: 2994.59 | G78: 0.27513672 | H78: 1 | I78: =J78*$C$32 -> 823.92167 | J78: =(F78*G78*H78)/$C$32 -> 1.830937
B79: 2 | C79: Rentals Proper team Fourways | F79: 3423.13 | G79: 0.40000005 | H79: 1 | I79: =J79*$C$32 -> 1369.2522 | J79: =(F79*G79*H79)/$C$32 -> 3.0427826
B80: 3 | C80: Dr A.S Bajomo | F80: 4034.65 | G80: 0.35258504 | H80: 1 | I80: =J80*$C$32 -> 1422.5572 | J80: =(F80*G80*H80)/$C$32 -> 3.1612383
B81: 4 | C81: Mectech Motors | F81: 6389.28 | G81: 0.33184584 | H81: 1 | I81: =J81*$C$32 -> 2120.256 | J81: =(F81*G81*H81)/$C$32 -> 4.71168
B82: 5 | C82: Natasha Mohunlal and Associates | F82: 2272.7 | G82: 0.32396632 | H82: 1 | I82: =J82*$C$32 -> 736.27826 | J82: =(F82*G82*H82)/$C$32 -> 1.6361739
B83: 6 | C83: R Protections | F83: 8100 | G83: 0.4 | H83: 1 | I83: =J83*$C$32 -> 3240 | J83: =(F83*G83*H83)/$C$32 -> 7.2
B84: 8 | C84: Chemstrat | F84: 14040 | G84: 0.4 | H84: 1 | I84: =J84*$C$32 -> 5616 | J84: =(F84*G84*H84)/$C$32 -> 12.48
B85: 9 | C85: Blue Hills | F85: 3895.65 | G85: 0.33750019 | H85: 1 | I85: =J85*$C$32 -> 1314.7826 | J85: =(F85*G85*H85)/$C$32 -> 2.9217391
H86: 1 | I86: =J86*$C$32 -> 0 | J86: =(F86*G86*H86)/$C$32 -> 0
C88: Once Off work:
B89: 1 | C89: Amagovu Trust | D89: Income Tax Number Registration | F89: 1391.3 | G89: 1 | H89: 1 | I89: =J89*$C$32 -> 1391.3 | J89: =(F89*G89*H89)/$C$32 -> 3.0917778
B90: 2 | C90: GUGULETHU FOUNDATION NPC | D90: Tax Profile Registration | F90: 1739.13 | G90: 1 | H90: 1 | I90: =J90*$C$32 -> 1739.13 | J90: =(F90*G90*H90)/$C$32 -> 3.8647333
B91: 3 | H91: 1 | I91: =J91*$C$32 -> 0 | J91: =(F91*G91*H91)/$C$32 -> 0
B92: 4 | H92: 1 | I92: =J92*$C$32 -> 0 | J92: =(F92*G92*H92)/$C$32 -> 0
B93: 5 | H93: 1 | I93: =J93*$C$32 -> 0 | J93: =(F93*G93*H93)/$C$32 -> 0
B94: 7 | H94: 1 | I94: =J94*$C$32 -> 0 | J94: =(F94*G94*H94)/$C$32 -> 0
B95: 8 | H95: 1 | I95: =J95*$C$32 -> 0 | J95: =(F95*G95*H95)/$C$32 -> 0
B96: 9 | H96: 1 | I96: =J96*$C$32 -> 0 | J96: =(F96*G96*H96)/$C$32 -> 0
B97: 10 | H97: 1 | I97: =J97*$C$32 -> 0 | J97: =(F97*G97*H97)/$C$32 -> 0
B98: 11 | H98: 1
B99: 12 | H99: 1
B100: 14 | H100: 1 | I100: =J100*$C$32 -> 0 | J100: =(F100*G100*H100)/$C$32 -> 0
B101: 15 | H101: 1 | I101: =J101*$C$32 -> 0 | J101: =(F101*G101*H101)/$C$32 -> 0
B102: 16 | H102: 1 | I102: =J102*$C$32 -> 0 | J102: =(F102*G102*H102)/$C$32 -> 0
B103: 17 | H103: 1 | I103: =J103*$C$32 -> 0 | J103: =(F103*G103*H103)/$C$32 -> 0
B104: 18 | H104: 1 | I104: =J104*$C$32 -> 0 | J104: =(F104*G104*H104)/$C$32 -> 0
B105: 19 | H105: 1 | I105: =J105*$C$32 -> 0 | J105: =(F105*G105*H105)/$C$32 -> 0
B106: 20 | H106: 1 | I106: =J106*$C$32 -> 0 | J106: =(F106*G106*H106)/$C$32 -> 0
F108: =SUM(F76:F107) -> 48280.43 | I108: =SUM(I78:I107) -> 19773.478 | J108: =SUM(J75:J107) -> 43.941062
E109: Excl VAT | F109: =100/115*F108 -> 41982.983 | H109: Excl VAT | I109: =100/115*I108 -> 17194.329
C114: Workflow Schedule for | E114: March | J114: 2026
C115: Charge Rate: | D115: Working Days in Month | F115: KPI % | G115: Hours per Day | H115: Monthly Budgeted Hours | I115: Total Scheduled Fees | J115: Hours Left
C116: =C73 -> 350 | D116: 21 | F116: =F73 -> 0.8 | G116: =G73 -> 8 | H116: =D116*G116*F116 -> 134.4 | I116: =I177 -> 0 | J116: =H116-J177 -> 134.4
C117: Entity Group \ Job Name | D117: Notes | F117: Estimated Fees for Job | G117: Team Members Job Completion % | H117: Pricing or Efficiency Override | I117: Budgeted WIP | J117: Job Budgeted Hrs | K117: Submission Date to client | L117: Accountants commnent on Due Date
C119: Monthly Recurring Work
C120: Mamangement Accounts:
B121: 1 | H121: 1 | I121: =J121*$C$32 -> 0 | J121: =(F121*G121*H121)/$C$32 -> 0
B122: 2 | H122: 1 | I122: =J122*$C$32 -> 0 | J122: =(F122*G122*H122)/$C$32 -> 0
B123: 3 | H123: 1 | I123: =J123*$C$32 -> 0 | J123: =(F123*G123*H123)/$C$32 -> 0
B124: 4 | H124: 1 | I124: =J124*$C$32 -> 0 | J124: =(F124*G124*H124)/$C$32 -> 0
B125: 5 | H125: 1 | I125: =J125*$C$32 -> 0 | J125: =(F125*G125*H125)/$C$32 -> 0
B126: 6 | H126: 1 | I126: =J126*$C$32 -> 0 | J126: =(F126*G126*H126)/$C$32 -> 0
B127: 7 | H127: 1 | I127: =J127*$C$32 -> 0 | J127: =(F127*G127*H127)/$C$32 -> 0
B128: 8 | H128: 1 | I128: =J128*$C$32 -> 0 | J128: =(F128*G128*H128)/$C$32 -> 0
B129: 9 | H129: 1 | I129: =J129*$C$32 -> 0 | J129: =(F129*G129*H129)/$C$32 -> 0
B130: 10 | H130: 1 | I130: =J130*$C$32 -> 0 | J130: =(F130*G130*H130)/$C$32 -> 0
H131: 1 | I131: =J131*$C$32 -> 0 | J131: =(F131*G131*H131)/$C$32 -> 0
C133: Payroll:
...

Sheet Katlego Jan - Dec '26
F3: Workflow Scheduling
B8: "A business is a commercial profitable enterprise that runs without you"
C10: Workflow Dashboard
B11: Senior Client Manager In Charge : | G11: Star Bongowongo
B12: Team Name: | G12: Katlego Mamatlepa
B14: Team Member: | D14: Katlego Mamatlepa | G14: Role: | J14: Junior Accountant
C15: Analysis: | E15: Fees: | G15: Analysis: | K15: Hours:
C16: Annual Fee Budget | E16: 408000 | G16: Annual Budgeted Hours | K16: =E16/C32 -> 1165.7143
C17: Scheduled Work and Jobs | E17: =+I64+I110+I179+I249+I319+I389+I459+I529+I599+I669+I739+I809 -> 5239.8489 | G17: Scheduled Hours | K17: =+J64+J110+J179+J249+J319+J389+J459+J529+J599+J669+J739+J809 -> 14.970997
C18: Over (Under) Scheduled Work | E18: =E17-E16 -> -402760.15 | G18: Over (Under) Scheduled Work | K18: =K17-K16 -> -1150.7433
B20: Remaining Hours to Fill:
D21: January | E21: =J32 -> 142.8 | F21: Apr | G21: =+J187 -> 129.2 | H21: July | I21: =+J397 -> 142.8 | J21: Oct | K21: =+J607 -> 156.4
D22: Feb | E22: =+J73 -> 121.029 | F22: May | G22: =+J257 -> 149.6 | H22: Aug | I22: =J467 -> 142.8 | J22: Nov | K22: =+J677 -> 136
D23: Mar | E23: =+J118 -> 142.8 | F23: June | G23: =+J327 -> 136 | H23: Sept | I23: =+J537 -> 142.8 | J23: Dec | K23: =+J747 -> 136
B25: Total Productivity Hours To Fill : | G25: =SUM(E21:E23)+SUM(G21:G23)+SUM(I21:I23)+SUM(K21:K23) -> 1678.229
C30: Workflow Schedule for | E30: January | J30: 2026
C31: Charge Rate: | D31: Working Days in Month | F31: KPI % | G31: Hours per Day | H31: Monthly Budgeted Hours | I31: Total Scheduled Fees | J31: Hours Left
C32: 350 | D32: 21 | F32: 0.85 | G32: 8 | H32: =D32*G32*F32 -> 142.8 | I32: =I64 -> 0 | J32: =H32-J64 -> 142.8
C33: Entity Group \ Job Name | D33: Notes | F33: Estimated Fees for Job | G33: Team Members Job Completion % | H33: Pricing or Efficiency Override | I33: Budgeted WIP | J33: Job Budgeted Hrs | K33: Submission Date to client | L33: Accountants commnent on Due Date
C35: Monthly Recurring Work
C36: Management Accounts:
C45: Once Off Work:
B46: 1 | H46: 1 | I46: =J46*$C$32 -> 0 | J46: =(F46*G46*H46)/$C$32 -> 0
B47: 2 | H47: 1 | I47: =J47*$C$32 -> 0 | J47: =(F47*G47*H47)/$C$32 -> 0
B48: 4 | H48: 1 | I48: =J48*$C$32 -> 0 | J48: =(F48*G48*H48)/$C$32 -> 0
B49: 5 | H49: 1 | I49: =J49*$C$32 -> 0 | J49: =(F49*G49*H49)/$C$32 -> 0
B50: 6 | H50: 1 | I50: =J50*$C$32 -> 0 | J50: =(F50*G50*H50)/$C$32 -> 0
B51: 7 | H51: 1 | I51: =J51*$C$32 -> 0 | J51: =(F51*G51*H51)/$C$32 -> 0
B52: 8 | H52: 1 | I52: =J52*$C$32 -> 0 | J52: =(F52*G52*H52)/$C$32 -> 0
B53: 9 | H53: 1 | I53: =J53*$C$32 -> 0 | J53: =(F53*G53*H53)/$C$32 -> 0
B54: 10 | H54: 1 | I54: =J54*$C$32 -> 0 | J54: =(F54*G54*H54)/$C$32 -> 0
B55: 11 | H55: 1 | I55: =J55*$C$32 -> 0 | J55: =(F55*G55*H55)/$C$32 -> 0
B56: 12 | H56: 1 | I56: =J56*$C$32 -> 0 | J56: =(F56*G56*H56)/$C$32 -> 0
B57: 13 | H57: 1 | I57: =J57*$C$32 -> 0 | J57: =(F57*G57*H57)/$C$32 -> 0
... B62: 20 | H62: 1 | I62: =J62*$C$32 -> 0 | J62: =(F62*G62*H62)/$C$32 -> 0
F64: =SUM(F37:F63) -> 0 | I64: =SUM(I35:I63) -> 0 | J64: =SUM(J34:J63) -> 0
E65: Excl VAT | F65: =100/115*F64 -> 0 | H65: Excl VAT | I65: =100/115*I64 -> 0
C71: Workflow Schedule for | E71: February | J71: 2026
C72: Charge Rate: | D72: Working Days in Month | F72: KPI % | G72: Hours per Day | H72: Monthly Budgeted Hours | I72: Total Scheduled Fees | J72: Hours Left
C73: =C32 -> 350 | D73: 20 | F73: =F32 -> 0.85 | G73: =G32 -> 8 | H73: =D73*G73*F73 -> 136 | I73: =I110 -> 5239.8489 | J73: =H73-J110 -> 121.029
C74: Entity Group \ Job Name | D74: Notes | F74: Estimated Fees for Job | G74: Team Members Job Completion % | H74: Pricing or Efficiency Override | I74: Budgeted WIP | J74: Job Budgeted Hrs | K74: Submission Date to client | L74: Accountants commnent on Due Date
C76: Monthly Recurring Work
C77: Management Accounts:
B78: 1 | C78: Depesh Cara - Rudzi | F78: 3947.826 | G78: ='Work Component Split'!K31 -> 0.088146259 | H78: 1 | I78: =J78*$C$32 -> 347.9861 | J78: =(F78*G78*H78)/$C$32 -> 0.99424599
B79: 2 | C79: TMM TECH -Rudzi | F79: 3549.91 | G79: ='Work Component Split'!K35 -> 0.10000009 | H79: 1 | I79: =J79*$C$32 -> 354.9913 | J79: =(F79*G79*H79)/$C$32 -> 1.0142609
B80: 3 | C80: Recovery Advisors - Kenneth | F80: 2430 | G80: 0.4 | H80: 1 | I80: =J80*$C$32 -> 972 | J80: =(F80*G80*H80)/$C$32 -> 2.7771429
B81: 4 | C81: Luk capital - Tatenda | F81: 2596.51 | G81: 0.39999967 | H81: 1 | I81: =J81*$C$32 -> 1038.6031 | J81: =(F81*G81*H81)/$C$32 -> 2.9674375
B82: 5 | C82: MMFS - Kenneth | F82: 4180 | G82: 0.36172249 | H82: 1 | I82: =J82*$C$32 -> 1512 | J82: =(F82*G82*H82)/$C$32 -> 4.32
B83: 6 | C83: Katomax Investments - Rudzi | F83: 2535.67 | G83: 0.40000015 | H83: 1 | I83: =J83*$C$32 -> 1014.2684 | J83: =(F83*G83*H83)/$C$32 -> 2.8979097
B84: 7 | H84: 1 | I84: =J84*$C$32 -> 0 | J84: =(F84*G84*H84)/$C$32 -> 0
B85: 8 | H85: 1 | I85: =J85*$C$32 -> 0 | J85: =(F85*G85*H85)/$C$32 -> 0
B86: 9 | H86: 1 | I86: =J86*$C$32 -> 0 | J86: =(F86*G86*H86)/$C$32 -> 0
B87: 10 | H87: 1 | I87: =J87*$C$32 -> 0 | J87: =(F87*G87*H87)/$C$32 -> 0
C90: Once Off work:
B91: 1 | H91: 1 | I91: =J91*$C$32 -> 0 | J91: =(F91*G91*H91)/$C$32 -> 0
B92: 2 | H92: 1 | I92: =J92*$C$32 -> 0 | J92: =(F92*G92*H92)/$C$32 -> 0
B93: 3 | H93: 1 | I93: =J93*$C$32 -> 0 | J93: =(F93*G93*H93)/$C$32 -> 0
B94: 4 | H94: 1 | I94: =J94*$C$32 -> 0 | J94: =(F94*G94*H94)/$C$32 -> 0
B95: 5 | H95: 1 | I95: =J95*$C$32 -> 0 | J95: =(F95*G95*H95)/$C$32 -> 0
B96: 7 | H96: 1 | I96: =J96*$C$32 -> 0 | J96: =(F96*G96*H96)/$C$32 -> 0
B97: 8 | H97: 1 | I97: =J97*$C$32 -> 0 | J97: =(F97*G97*H97)/$C$32 -> 0
B98: 9 | H98: 1 | I98: =J98*$C$32 -> 0 | J98: =(F98*G98*H98)/$C$32 -> 0
B99: 10 | H99: 1 | I99: =J99*$C$32 -> 0 | J99: =(F99*G99*H99)/$C$32 -> 0
B100: 11 | H100: 1
B101: 12 | H101: 1
B102: 14 | H102: 1 | I102: =J102*$C$32 -> 0 | J102: =(F102*G102*H102)/$C$32 -> 0
B103: 15 | H103: 1 | I103: =J103*$C$32 -> 0 | J103: =(F103*G103*H103)/$C$32 -> 0
B104: 16 | H104: 1 | I104: =J104*$C$32 -> 0 | J104: =(F104*G104*H104)/$C$32 -> 0
B105: 17 | H105: 1 | I105: =J105*$C$32 -> 0 | J105: =(F105*G105*H105)/$C$32 -> 0
B106: 18 | H106: 1 | I106: =J106*$C$32 -> 0 | J106: =(F106*G106*H106)/$C$32 -> 0
B107: 19 | H107: 1 | I107: =J107*$C$32 -> 0 | J107: =(F107*G107*H107)/$C$32 -> 0
B108: 20 | H108: 1 | I108: =J108*$C$32 -> 0 | J108: =(F108*G108*H108)/$C$32 -> 0
F110: =SUM(F76:F109) -> 19239.916 | I110: =SUM(I78:I109) -> 5239.8489 | J110: =SUM(J75:J109) -> 14.970997
E111: Excl VAT | F111: =100/115*F110 -> 16730.362 | H111: Excl VAT | I111: =100/115*I110 -> 4556.3904
C116: Workflow Schedule for | E116: March | J116: 2026
C117: Charge Rate: | D117: Working Days in Month | F117: KPI % | G117: Hours per Day | H117: Monthly Budgeted Hours | I117: Total Scheduled Fees | J117: Hours Left
C118: =C73 -> 350 | D118: 21 | F118: =F73 -> 0.85 | G118: =G73 -> 8 | H118: =D118*G118*F118 -> 142.8 | I118: =I179 -> 0 | J118: =H118-J179 -> 142.8
C119: Entity Group \ Job Name | D119: Notes | F119: Estimated Fees for Job | G119: Team Members Job Completion % | H119: Pricing or Efficiency Override | I119: Budgeted WIP | J119: Job Budgeted Hrs | K119: Submission Date to client | L119: Accountants commnent on Due Date
C121: Monthly Recurring Work
C122: Mamangement Accounts:
B123: 1 | H123: 1 | I123: =J123*$C$32 -> 0 | J123: =(F123*G123*H123)/$C$32 -> 0
B124: 2 | H124: 1 | I124: =J124*$C$32 -> 0 | J124: =(F124*G124*H124)/$C$32 -> 0
B125: 3 | H125: 1 | I125: =J125*$C$32 -> 0 | J125: =(F125*G125*H125)/$C$32 -> 0
B126: 4 | H126: 1 | I126: =J126*$C$32 -> 0 | J126: =(F126*G126*H126)/$C$32 -> 0
B127: 5 | H127: 1 | I127: =J127*$C$32 -> 0 | J127: =(F127*G127*H127)/$C$32 -> 0
B128: 6 | H128: 1 | I128: =J128*$C$32 -> 0 | J128: =(F128*G128*H128)/$C$32 -> 0
B129: 7 | H129: 1 | I129: =J129*$C$32 -> 0 | J129: =(F129*G129*H129)/$C$32 -> 0
B130: 8 | H130: 1 | I130: =J130*$C$32 -> 0 | J130: =(F130*G130*H130)/$C$32 -> 0
B131: 9 | H131: 1 | I131: =J131*$C$32 -> 0 | J131: =(F131*G131*H131)/$C$32 -> 0
B132: 10 | H132: 1 | I132: =J132*$C$32 -> 0 | J132: =(F132*G132*H132)/$C$32 -> 0
H133: 1 | I133: =J133*$C$32 -> 0 | J133: =(F133*G133*H133)/$C$32 -> 0
C135: Payroll:
B136: 1 | H136: 1 | I136: =J136*$C$32 -> 0 | J136: =(F136*G136*H136)/$C$32 -> 0
B137: 2 | H137: 1 | I137: =J137*$C$32 -> 0 | J137: =(F137*G137*H137)/$C$32 -> 0
B138: 3 | H138: 1 | I138: =J138*$C$32 -> 0 | J138: =(F138*G138*H138)/$C$32 -> 0
B139: 5 | H139: 1 | I139: =J139*$C$32 -> 0 | J139: =(F139*G139*H139)/$C$32 -> 0
B140: 6 | H140: 1 | I140: =J140*$C$32 -> 0 | J140: =(F140*G140*H140)/$C$32 -> 0
B141: 7 | H141: 1 | I141: =J141*$C$32 -> 0 | J141: =(F141*G141*H141)/$C$32 -> 0
B142: 8 | H142: 1 | I142: =J142*$C$32 -> 0 | J142: =(F142*G142*H142)/$C$32 -> 0
B143: 9 | H143: 1 | I143: =J143*$C$32 -> 0 | J143: =(F143*G143*H143)/$C$32 -> 0
...

Sheet Bruce Jan - Dec '26
F3: Workflow Scheduling
B8: "A business is a commercial profitable enterprise that runs without you"
C10: Workflow Dashboard
B11: Senior Client Manager In Charge : | G11: Star Bongowongo
B12: Team Name: | G12: Bruce Saurombe
B14: Team Member: | D14: Bruce | G14: Role: | J14: Accountant
C15: Analysis: | E15: Fees: | G15: Analysis: | K15: Hours:
C16: Annual Fee Budget | E16: =54720*12 -> 656640 | G16: Annual Budgeted Hours | K16: =E16/C32 -> 1459.2
C17: Scheduled Work and Jobs | E17: =+I65+I110+I179+I249+I319+I389+I459+I529+I599+I669+I739+I809 -> #VALUE! | G17: Scheduled Hours | K17: =+J65+J110+J179+J249+J319+J389+J459+J529+J599+J669+J739+J809 -> #VALUE!
C18: Over (Under) Scheduled Work | E18: =E17-E16 -> #VALUE! | G18: Over (Under) Scheduled Work | K18: =K17-K16 -> #VALUE!
B20: Remaining Hours to Fill:
D21: January | E21: =J32 -> #VALUE! | F21: Apr | G21: =+J187 -> 121.6 | H21: July | I21: =+J397 -> 134.4 | J21: Oct | K21: =+J607 -> 147.2
D22: Feb | E22: =+J74 -> 18.998129 | F22: May | G22: =+J257 -> 140.8 | H22: Aug | I22: =J467 -> 134.4 | J22: Nov | K22: =+J677 -> 128
D23: Mar | E23: =+J118 -> 134.4 | F23: June | G23: =+J327 -> 128 | H23: Sept | I23: =+J537 -> 134.4 | J23: Dec | K23: =+J747 -> 128
B25: Total Productivity Hours To Fill : | G25: =SUM(E21:E23)+SUM(G21:G23)+SUM(I21:I23)+SUM(K21:K23) -> #VALUE!
C30: Workflow Schedule for | E30: January | J30: 2026
C31: Charge Rate: | D31: Working Days in Month | F31: KPI % | G31: Hours per Day | H31: Monthly Budgeted Hours | I31: Total Scheduled Fees | J31: Hours Left
C32: 450 | D32: 21 | F32: 0.8 | G32: 8 | H32: =D32*G32*F32 -> 134.4 | I32: =I65 -> #VALUE! | J32: =H32-J65 -> #VALUE!
C33: Entity Group \ Job Name | D33: Notes | F33: Estimated Fees for Job | G33: Team Members Job Completion % | H33: Pricing or Efficiency Override | I33: Budgeted WIP | J33: Job Budgeted Hrs | K33: Submission Date to client | L33: Accountants commnent on Due Date
C35: Monthly Recurring Work
C36: Management Accounts:
B37: 1 | C37: Vera Step | F37: 2943 | G37: 0.4 | H37: 1 | I37: =J37*$C$32 -> 1177.2 | J37: =(F37*G37*H37)/$C$32 -> 2.616
B38: 2 | C38: Moja Legal Consulting and Investment (Pty) Ltd | F38: 2028.52 | G38: 0.4 | H38: 1 | I38: =J38*$C$32 -> 811.408 | J38: =(F38*G38*H38)/$C$32 -> 1.8031289
B39: 3 | C39: Bona By Wenzy | F39: 1890 | G39: 0.4 | H39: 1 | I39: =J39*$C$32 -> 756 | J39: =(F39*G39*H39)/$C$32 -> 1.68
B40: 4 | C40: Mawela Simpson | F40: 3888 | G40: 0.4 | H40: 1 | I40: =J40*$C$32 -> 1555.2 | J40: =(F40*G40*H40)/$C$32 -> 3.456
B41: 5 | C41: MGI Global | F41: 2916 | G41: 0.4 | H41: 1 | I41: =J41*$C$32 -> 1166.4 | J41: =(F41*G41*H41)/$C$32 -> 2.592
B42: 6 | C42: Plush Spaces | F42: 2303.5043 | G42: 0.33357871 | H42: 0 | I42: =J42*$C$32 -> 0 | J42: =(F42*G42*H42)/$C$32 -> 0
B43: 7 | C43: Swiiff | F43: 2916 | G43: 0.4 | H43: 1 | I43: =J43*$C$32 -> 1166.4 | J43: =(F43*G43*H43)/$C$32 -> 2.592
B44: 8 | C44: Fitness Reenvisioned | F44: 1572.1 | G44: 0.40000111 | H44: 1 | I44: =J44*$C$32 -> 628.84174 | J44: =(F44*G44*H44)/$C$32 -> 1.3974261
B45: 9 | C45: Susbtream | F45: 5352.48 | G45: 0.4 | H45: 1 | I45: =J45*$C$32 -> 2140.992 | J45: =(F45*G45*H45)/$C$32 -> 4.75776
C48: Once Off work:
B49: 1 | C49: Aquity | F49: R | G49: 0.4 | H49: 1 | I49: =J49*$C$32 -> #VALUE! | J49: =(F49*G49*H49)/$C$32 -> #VALUE!
B50: 2 | F50: 9200 | G50: 0.9 | H50: 1 | I50: =J50*$C$32 -> 8280 | J50: =(F50*G50*H50)/$C$32 -> 18.4
B51: 6 | H51: 1 | I51: =J51*$C$32 -> 0 | J51: =(F51*G51*H51)/$C$32 -> 0
B52: 7 | H52: 1 | I52: =J52*$C$32 -> 0 | J52: =(F52*G52*H52)/$C$32 -> 0
B53: 8 | H53: 1 | I53: =J53*$C$32 -> 0 | J53: =(F53*G53*H53)/$C$32 -> 0
B54: 9 | H54: 1 | I54: =J54*$C$32 -> 0 | J54: =(F54*G54*H54)/$C$32 -> 0
B55: 10 | H55: 1 | I55: =J55*$C$32 -> 0 | J55: =(F55*G55*H55)/$C$32 -> 0
B56: 11 | H56: 1 | I56: =J56*$C$32 -> 0 | J56: =(F56*G56*H56)/$C$32 -> 0
B57: 12 | H57: 1 | I57: =J57*$C$32 -> 0 | J57: =(F57*G57*H57)/$C$32 -> 0
B58: 13 | H58: 1 | I58: =J58*$C$32 -> 0 | J58: =(F58*G58*H58)/$C$32 -> 0
B59: 14 | H59: 1 | I59: =J59*$C$32 -> 0 | J59: =(F59*G59*H59)/$C$32 -> 0
B60: 16 | H60: 1 | I60: =J60*$C$32 -> 0 | J60: =(F60*G60*H60)/$C$32 -> 0
B61: 17 | H61: 1 | I61: =J61*$C$32 -> 0 | J61: =(F61*G61*H61)/$C$32 -> 0
B62: 19 | H62: 1 | I62: =J62*$C$32 -> 0 | J62: =(F62*G62*H62)/$C$32 -> 0
B63: 20 | H63: 1 | I63: =J63*$C$32 -> 0 | J63: =(F63*G63*H63)/$C$32 -> 0
F65: =SUM(F37:F64) -> 35009.604 | I65: =SUM(I35:I64) -> #VALUE! | J65: =SUM(J34:J64) -> #VALUE!
E66: Excl VAT | F66: =100/115*F65 -> 30443.134 | H66: Excl VAT | I66: =100/115*I65 -> #VALUE!
C72: Workflow Schedule for | E72: February | J72: 2026
C73: Charge Rate: | D73: Working Days in Month | F73: KPI % | G73: Hours per Day | H73: Monthly Budgeted Hours | I73: Total Scheduled Fees | J73: Hours Left
C74: =C32 -> 450 | D74: 20 | F74: =F32 -> 0.8 | G74: =G32 -> 8 | H74: =D74*G74*F74 -> 128 | I74: =I110 -> 49050.842 | J74: =H74-J110 -> 18.998129
C75: Entity Group \ Job Name | D75: Notes | F75: Estimated Fees for Job | G75: Team Members Job Completion % | H75: Pricing or Efficiency Override | I75: Budgeted WIP | J75: Job Budgeted Hrs | K75: Submission Date to client | L75: Accountants commnent on Due Date
C77: Monthly Recurring Work
C78: Management Accounts:
B79: 1 | C79: Vera Step | F79: 2943 | G79: 0.4 | H79: 1 | I79: =J79*$C$32 -> 1177.2 | J79: =(F79*G79*H79)/$C$32 -> 2.616
B80: 2 | C80: Moja Legal Consulting and Investment (Pty) Ltd | F80: 2028.52 | G80: 0.4 | H80: 1 | I80: =J80*$C$32 -> 811.408 | J80: =(F80*G80*H80)/$C$32 -> 1.8031289
B81: 3 | C81: Bona By Wenzy | F81: 1890 | G81: 0.4 | H81: 1 | I81: =J81*$C$32 -> 756 | J81: =(F81*G81*H81)/$C$32 -> 1.68
B82: 4 | C82: Mawela Simpson | F82: 3888 | G82: 0.4 | H82: 1 | I82: =J82*$C$32 -> 1555.2 | J82: =(F82*G82*H82)/$C$32 -> 3.456
B83: 5 | C83: MGI Global | F83: 2916 | G83: 0.4 | H83: 1 | I83: =J83*$C$32 -> 1166.4 | J83: =(F83*G83*H83)/$C$32 -> 2.592
B84: 6 | C84: Plush Spaces | F84: 2303.5043 | G84: 0.33357871 | H84: 1 | I84: =J84*$C$32 -> 768.4 | J84: =(F84*G84*H84)/$C$32 -> 1.7075556
B85: 7 | C85: Swiiff | F85: 2916 | G85: 0.4 | H85: 1 | I85: =J85*$C$32 -> 1166.4 | J85: =(F85*G85*H85)/$C$32 -> 2.592
B86: 8 | C86: Fitness Reenvisioned | F86: 1572.1 | G86: 0.40000111 | H86: 1 | I86: =J86*$C$32 -> 628.84174 | J86: =(F86*G86*H86)/$C$32 -> 1.3974261
B87: 9 | C87: Susbtream | F87: 5352.48 | G87: 0.4 | H87: 1 | I87: =J87*$C$32 -> 2140.992 | J87: =(F87*G87*H87)/$C$32 -> 4.75776
C90: Once Off work:
B91: 1 | C91: Heavens Gate | D91: Managemet Accounts | F91: 76500 | G91: 0.4 | H91: 1 | I91: =J91*$C$32 -> 30600 | J91: =(F91*G91*H91)/$C$32 -> 68
B92: 2 | C92: Heavens Gate | D92: Annual Financial Statements | F92: 9200 | G92: 0.9 | H92: 1 | I92: =J92*$C$32 -> 8280 | J92: =(F92*G92*H92)/$C$32 -> 18.4
B93: 3 | H93: 1 | I93: =J93*$C$32 -> 0 | J93: =(F93*G93*H93)/$C$32 -> 0
B94: 4 | H94: 1 | I94: =J94*$C$32 -> 0 | J94: =(F94*G94*H94)/$C$32 -> 0
B95: 5 | H95: 1 | I95: =J95*$C$32 -> 0 | J95: =(F95*G95*H95)/$C$32 -> 0
B96: 7 | H96: 1 | I96: =J96*$C$32 -> 0 | J96: =(F96*G96*H96)/$C$32 -> 0
B97: 8 | H97: 1 | I97: =J97*$C$32 -> 0 | J97: =(F97*G97*H97)/$C$32 -> 0
B98: 9 | H98: 1 | I98: =J98*$C$32 -> 0 | J98: =(F98*G98*H98)/$C$32 -> 0
B99: 10 | H99: 1 | I99: =J99*$C$32 -> 0 | J99: =(F99*G99*H99)/$C$32 -> 0
B100: 11 | H100: 1
B101: 12 | H101: 1
B102: 14 | H102: 1 | I102: =J102*$C$32 -> 0 | J102: =(F102*G102*H102)/$C$32 -> 0
B103: 15 | H103: 1 | I103: =J103*$C$32 -> 0 | J103: =(F103*G103*H103)/$C$32 -> 0
B104: 16 | H104: 1 | I104: =J104*$C$32 -> 0 | J104: =(F104*G104*H104)/$C$32 -> 0
B105: 17 | H105: 1 | I105: =J105*$C$32 -> 0 | J105: =(F105*G105*H105)/$C$32 -> 0
B106: 18 | H106: 1 | I106: =J106*$C$32 -> 0 | J106: =(F106*G106*H106)/$C$32 -> 0
B107: 19 | H107: 1 | I107: =J107*$C$32 -> 0 | J107: =(F107*G107*H107)/$C$32 -> 0
B108: 20 | H108: 1 | I108: =J108*$C$32 -> 0 | J108: =(F108*G108*H108)/$C$32 -> 0
F110: =SUM(F77:F109) -> 111509.6 | I110: =SUM(I79:I109) -> 49050.842 | J110: =SUM(J76:J109) -> 109.00187
E111: Excl VAT | F111: =100/115*F110 -> 96964.873 | H111: Excl VAT | I111: =100/115*I110 -> 42652.906
C116: Workflow Schedule for | E116: March | J116: 2026
C117: Charge Rate: | D117: Working Days in Month | F117: KPI % | G117: Hours per Day | H117: Monthly Budgeted Hours | I117: Total Scheduled Fees | J117: Hours Left
C118: =C74 -> 450 | D118: 21 | F118: =F74 -> 0.8 | G118: =G74 -> 8 | H118: =D118*G118*F118 -> 134.4 | I118: =I179 -> 0 | J118: =H118-J179 -> 134.4
C119: Entity Group \ Job Name | D119: Notes | F119: Estimated Fees for Job | G119: Team Members Job Completion % | H119: Pricing or Efficiency Override | I119: Budgeted WIP | J119: Job Budgeted Hrs | K119: Submission Date to client | L119: Accountants commnent on Due Date
C121: Monthly Recurring Work
C122: Mamangement Accounts:
B123: 1 | H123: 1 | I123: =J123*$C$32 -> 0 | J123: =(F123*G123*H123)/$C$32 -> 0
B124: 2 | H124: 1 | I124: =J124*$C$32 -> 0 | J124: =(F124*G124*H124)/$C$32 -> 0
B125: 3 | H125: 1 | I125: =J125*$C$32 -> 0 | J125: =(F125*G125*H125)/$C$32 -> 0
B126: 4 | H126: 1 | I126: =J126*$C$32 -> 0 | J126: =(F126*G126*H126)/$C$32 -> 0
B127: 5 | H127: 1 | I127: =J127*$C$32 -> 0 | J127: =(F127*G127*H127)/$C$32 -> 0
B128: 6 | H128: 1 | I128: =J128*$C$32 -> 0 | J128: =(F128*G128*H128)/$C$32 -> 0
B129: 7 | H129: 1 | I129: =J129*$C$32 -> 0 | J129: =(F129*G129*H129)/$C$32 -> 0
B130: 8 | H130: 1 | I130: =J130*$C$32 -> 0 | J130: =(F130*G130*H130)/$C$32 -> 0
B131: 9 | H131: 1 | I131: =J131*$C$32 -> 0 | J131: =(F131*G131*H131)/$C$32 -> 0
B132: 10 | H132: 1 | I132: =J132*$C$32 -> 0 | J132: =(F132*G132*H132)/$C$32 -> 0
...

Sheet Christine Jan - Dec '26
F3: Workflow Scheduling
B8: "A business is a commercial profitable enterprise that runs without you"
C10: Workflow Dashboard
B11: Senior Client Manager In Charge : | G11: Star Bongowongo
B12: Team Name: | G12: Christine Mashava
B14: Team Member: | D14: Christine | G14: Role: | J14: Junior Accountant
C15: Analysis: | E15: Fees: | G15: Analysis: | K15: Hours:
C16: Annual Fee Budget | E16: =50512*12 -> 606144 | G16: Annual Budgeted Hours | K16: =E16/C32 -> 1346.9867
C17: Scheduled Work and Jobs | E17: =+I88+I154+I223+I293+I363+I433+I503+I573+I643+I713+I783+I853 -> 89730.791 | G17: Scheduled Hours | K17: =+J88+J154+J223+J293+J363+J433+J503+J573+J643+J713+J783+J853 -> 199.40176
C18: Over (Under) Scheduled Work | E18: =E17-E16 -> -516413.21 | G18: Over (Under) Scheduled Work | K18: =K17-K16 -> -1147.5849
B20: Remaining Hours to Fill:
D21: January | E21: =J32 -> 49.57851 | F21: Apr | G21: =+J231 -> 121.6 | H21: July | I21: =+J441 -> 134.4 | J21: Oct | K21: =+J651 -> 147.2
D22: Feb | E22: =+J97 -> 13.419732 | F22: May | G22: =+J301 -> 140.8 | H22: Aug | I22: =J511 -> 134.4 | J22: Nov | K22: =+J721 -> 128
D23: Mar | E23: =+J162 -> 134.4 | F23: June | G23: =+J371 -> 128 | H23: Sept | I23: =+J581 -> 134.4 | J23: Dec | K23: =+J791 -> 128
B25: Total Productivity Hours To Fill : | G25: =SUM(E21:E23)+SUM(G21:G23)+SUM(I21:I23)+SUM(K21:K23) -> 1394.1982
C30: Workflow Schedule for | E30: January | J30: 2026
C31: Charge Rate: | D31: Working Days in Month | F31: KPI % | G31: Hours per Day | H31: Monthly Budgeted Hours | I31: Total Scheduled Fees | J31: Hours Left
C32: 450 | D32: 21 | F32: 0.8 | G32: 8 | H32: =D32*G32*F32 -> 134.4 | I32: =I88 -> 38169.671 | J32: =H32-J88 -> 49.57851
C33: Entity Group \ Job Name | D33: Notes | F33: Estimated Fees for Job | G33: Team Members Job Completion % | H33: Pricing or Efficiency Override | I33: Budgeted WIP | J33: Job Budgeted Hrs | K33: Submission Date to client | L33: Accountants commnent on Due Date
C35: Monthly Recurring Work
C36: Management Accounts:
C40: Payroll:
B41: 1 | C41: Maxopani Holdings | F41: 26548.8 | G41: 0.3 | H41: 1 | I41: =J41*$C$32 -> 7964.64 | J41: =(F41*G41*H41)/$C$32 -> 17.6992
B42: =B41+1 -> 2 | C42: Makhubela Incorporated | F42: 2351.77 | G42: 0.21 | H42: 1 | I42: =J42*$C$32 -> 493.8717 | J42: =(F42*G42*H42)/$C$32 -> 1.0974927
B43: =B42+1 -> 3 | C43: Destiny Finance (Pty) Ltd | F43: 10198.79 | G43: 0.35 | H43: 1 | I43: =J43*$C$32 -> 3569.5765 | J43: =(F43*G43*H43)/$C$32 -> 7.9323922
B44: =B43+1 -> 4 | C44: DR WW NGWATA PRACTICE INC | F44: 3649.02 | G44: 0.13 | H44: 1 | I44: =J44*$C$32 -> 474.3726 | J44: =(F44*G44*H44)/$C$32 -> 1.0541613
B45: =B44+1 -> 5 | C45: Bixa Consulting | F45: 3294.5 | G45: 0.15 | H45: 1 | I45: =J45*$C$32 -> 494.175 | J45: =(F45*G45*H45)/$C$32 -> 1.0981667
B46: =B45+1 -> 6 | C46: Giant Bee Logistics Pty Ltd | F46: 6662.57 | G46: 0.19 | H46: 1 | I46: =J46*$C$32 -> 1265.8883 | J46: =(F46*G46*H46)/$C$32 -> 2.8130851
B47: =B46+1 -> 7 | C47: Astra Matellite | F47: ='Work Component Split'!F27 -> 5328.2935 | G47: 0 | H47: 1 | I47: =J47*$C$32 -> 0 | J47: =(F47*G47*H47)/$C$32 -> 0
B48: =B47+1 -> 8 | C48: CREATIVE VALLEY NURSERY SCHOOL | F48: 3443.7748 | G48: 0.31 | H48: 1 | I48: =J48*$C$32 -> 1067.5702 | J48: =(F48*G48*H48)/$C$32 -> 2.3723782
B49: =B48+1 -> 9 | C49: Depesh Cara | F49: 540 | G49: 1 | H49: 1 | I49: =J49*$C$32 -> 540 | J49: =(F49*G49*H49)/$C$32 -> 1.2
B50: =B49+1 -> 10 | C50: Dr A.S Bajomo | F50: 4639.852 | G50: 0.12 | H50: 1 | I50: =J50*$C$32 -> 556.78224 | J50: =(F50*G50*H50)/$C$32 -> 1.2372939
B51: =B50+1 -> 11 | C51: Mectech Motors | F51: 7347.672 | G51: 0.17 | H51: 1 | I51: =J51*$C$32 -> 1249.1042 | J51: =(F51*G51*H51)/$C$32 -> 2.7757872
B52: =B51+1 -> 12 | C52: Blue Hill | F52: 4480 | G52: 0.16 | H52: 1 | I52: =J52*$C$32 -> 716.8 | J52: =(F52*G52*H52)/$C$32 -> 1.5928889
B53: =B52+1 -> 13 | C53: Natasha Mohunlal | F53: 2613.6 | G53: 0.19 | H53: 1 | I53: =J53*$C$32 -> 496.584 | J53: =(F53*G53*H53)/$C$32 -> 1.10352
B54: =B53+1 -> 14 | C54: MMFS | F54: 4807 | G54: 0.1 | H54: 1 | I54: =J54*$C$32 -> 480.7 | J54: =(F54*G54*H54)/$C$32 -> 1.0682222
B55: =B54+1 -> 15 | C55: CN Freight | F55: 4708.216 | G55: 0.12 | H55: 1 | I55: =J55*$C$32 -> 564.98592 | J55: =(F55*G55*H55)/$C$32 -> 1.2555243
B56: =B55+1 -> 16 | C56: Promote Balance | F56: 496.8 | G56: 1 | H56: 1 | I56: =J56*$C$32 -> 496.8 | J56: =(F56*G56*H56)/$C$32 -> 1.104
B57: =B56+1 -> 17 | C57: Bophelong | F57: 2918.7 | G57: 1 | H57: 1 | I57: =J57*$C$32 -> 2918.7 | J57: =(F57*G57*H57)/$C$32 -> 6.486
B58: =B57+1 -> 18 | C58: Makhubela Incorporated | F58: 500 | G58: 1 | H58: 1 | I58: =J58*$C$32 -> 500 | J58: =(F58*G58*H58)/$C$32 -> 1.1111111
B59: =B58+1 -> 19 | C59: Maksure Risk Solutions | F59: 7781.4 | G59: 1 | H59: 1 | I59: =J59*$C$32 -> 7781.4 | J59: =(F59*G59*H59)/$C$32 -> 17.292
... B65: =B64+1 -> 25 | C65: Work co | F65: 993.6 | G65: 1 | H65: 1 | I65: =J65*$C$32 -> 993.6 | J65: =(F65*G65*H65)/$C$32 -> 2.208
C68: Once Off Clients
B69: 1 | C69: Affinity Risk Solutions | D69: Tax submission | H69: 1 | I69: =J69*$C$32 -> 0 | J69: =(F70*G69*H69)/$C$32 -> 0
B70: 2 | C70: Bixa Consulting (Pty) Ltd | D70: changing shareholders and the company structure | H70: 1 | I70: =J70*$C$32 -> 0 | J70: =(F71*G70*H70)/$C$32 -> 0
B71: 3 | C71: DAWN RISK MANAGING AGENCY (PTY) LTD | D71: Auditors appointment and confirmation letter | H71: 1 | I71: =J71*$C$32 -> 0 | J71: =(F72*G71*H71)/$C$32 -> 0
B72: 4 | C72: GLN Properties (Pty) Ltd | D72: preparing schedule,EMP 201 | H72: 1 | I72: =J72*$C$32 -> 0 | J72: =(F73*G72*H72)/$C$32 -> 0
B73: 5 | C73: Hambo Lwethu Travel (Pty) Ltd | D73: emp 201 | H73: 1 | I73: =J73*$C$32 -> 0 | J73: =(F74*G73*H73)/$C$32 -> 0
B74: 6 | C74: Innovateher Solutions (Pty) Ltd | D74: beneficial ownership | H74: 1 | I74: =J74*$C$32 -> 0 | J74: =(F75*G74*H74)/$C$32 -> 0
B75: 7 | C75: Joren Communications (Pty) Ltd | D75: Processing payroll , Ufiling Submissions | H75: 1 | I75: =J75*$C$32 -> 0 | J75: =(F76*G75*H75)/$C$32 -> 0
B76: 8 | C76: Moja Legal Consulting and Investment (Pty) Ltd | D76: payroll setup and payroll | H76: 1 | I76: =J76*$C$32 -> 0 | J76: =(F77*G76*H76)/$C$32 -> 0
B77: 9 | C77: MP Zwane And Associates | D77: Audit | H77: 1 | I77: =J77*$C$32 -> 0 | J77: =(F78*G77*H77)/$C$32 -> 0
B78: 10 | C78: Rentals Properteam Fourways | D78: compiling documents for COIDA , emp 201,staement converting and sorting for PAYE | H78: 1 | I78: =J78*$C$32 -> 0 | J78: =(F79*G78*H78)/$C$32 -> 0
B79: 11 | C79: Sefton Engineering (Pty) Ltd | D79: share register and mandate , CIPC return 2021 to 2025 , address change for company and director , company reinstatement | H79: 1 | I79: =J79*$C$32 -> 0 | J79: =(F80*G79*H79)/$C$32 -> 0
B80: 12 | C80: SMECPT | D80: Processing payroll | H80: 1 | I80: =J80*$C$32 -> 0 | J80: =(F81*G80*H80)/$C$32 -> 0
B81: 13 | C81: Wood Wharf Investments | D81: company registration | H81: 1 | I81: =J81*$C$32 -> 0 | J81: =(F82*G81*H81)/$C$32 -> 0
B82: 14 | H82: 1 | I82: =J82*$C$32 -> 0 | J82: =(F83*G82*H82)/$C$32 -> 0
B83: 16 | H83: 1 | I83: =J83*$C$32 -> 0 | J83: =(F84*G83*H83)/$C$32 -> 0
B84: 17 | H84: 1 | I84: =J84*$C$32 -> 0 | J84: =(F85*G84*H84)/$C$32 -> 0
B85: 19 | H85: 1 | I85: =J85*$C$32 -> 0 | J85: =(F86*G85*H85)/$C$32 -> 0
B86: 20 | H86: 1 | I86: =J86*$C$32 -> 0 | J86: =(F87*G86*H86)/$C$32 -> 0
F88: =SUM(F37:F87) -> 108848.48 | I88: =SUM(I35:I87) -> 38169.671 | J88: =SUM(J34:J87) -> 84.82149
E89: Excl VAT | F89: =100/115*F88 -> 94650.851 | H89: Excl VAT | I89: =100/115*I88 -> 33191.018
C95: Workflow Schedule for | E95: February | J95: 2026
C96: Charge Rate: | D96: Working Days in Month | F96: KPI % | G96: Hours per Day | H96: Monthly Budgeted Hours | I96: Total Scheduled Fees | J96: Hours Left
C97: =C32 -> 450 | D97: 20 | F97: =F32 -> 0.8 | G97: =G32 -> 8 | H97: =D97*G97*F97 -> 128 | I97: =I154 -> 51561.121 | J97: =H97-J154 -> 13.419732
C98: Entity Group \ Job Name | D98: Notes | F98: Estimated Fees for Job | G98: Team Members Job Completion % | H98: Pricing or Efficiency Override | I98: Budgeted WIP | J98: Job Budgeted Hrs | K98: Submission Date to client | L98: Accountants commnent on Due Date
C100: Monthly Recurring Work
C101: Management Accounts:
B102: 1 | C102: CM Freelancing (Pty) Ltd | F102: ='Work Component Split'!F53 -> 3237.3 | G102: 1 | H102: 1 | I102: =J102*$C$32 -> 3237.3 | J102: =(F102*G102*H102)/$C$32 -> 7.194
B103: 2 | C103: EKSN ENGINEERING | F103: ='Work Component Split'!F54 -> 1784.59 | G103: 1 | H103: 1 | I103: =J103*$C$32 -> 1784.59 | J103: =(F103*G103*H103)/$C$32 -> 3.9657556
B104: 3 | C104: Spade | F104: ='Work Component Split'!F15 -> 0 | G104: 1 | H104: 1 | I104: =J104*$C$32 -> 0 | J104: =(F104*G104*H104)/$C$32 -> 0
C107: Payroll:
B108: 1 | C108: Maxopani Holdings | F108: 26548.8 | G108: 0.3 | H108: 1 | I108: =J108*$C$32 -> 7964.64 | J108: =(F108*G108*H108)/$C$32 -> 17.6992
B109: 2 | C109: Makhubela Incorporated | F109: 2351.77 | G109: 0.21 | H109: 1 | I109: =J109*$C$32 -> 493.8717 | J109: =(F109*G109*H109)/$C$32 -> 1.0974927
B110: 3 | C110: Destiny Finance (Pty) Ltd | F110: 10198.79 | G110: 0.35 | H110: 1 | I110: =J110*$C$32 -> 3569.5765 | J110: =(F110*G110*H110)/$C$32 -> 7.9323922
B111: 4 | C111: DR WW NGWATA PRACTICE INC | F111: 3649.02 | G111: 0.13 | H111: 1 | I111: =J111*$C$32 -> 474.3726 | J111: =(F111*G111*H111)/$C$32 -> 1.0541613
B112: 5 | C112: Bixa Consulting | F112: 3294.5 | G112: 0.15 | H112: 1 | I112: =J112*$C$32 -> 494.175 | J112: =(F112*G112*H112)/$C$32 -> 1.0981667
B113: 6 | C113: Giant Bee Logistics Pty Ltd | F113: 6662.57 | G113: 0.19 | H113: 1 | I113: =J113*$C$32 -> 1265.8883 | J113: =(F113*G113*H113)/$C$32 -> 2.8130851
B114: 7 | C114: Astra Matellite | F114: ='Work Component Split'!F27 -> 5328.2935 | G114: 0 | H114: 1 | I114: =J114*$C$32 -> 0 | J114: =(F114*G114*H114)/$C$32 -> 0
B115: 8 | C115: CREATIVE VALLEY NURSERY SCHOOL | F115: 3443.7748 | G115: 0.31 | H115: 1 | I115: =J115*$C$32 -> 1067.5702 | J115: =(F115*G115*H115)/$C$32 -> 2.3723782
B116: 9 | C116: Depesh Cara | F116: 540 | G116: 1 | H116: 1 | I116: =J116*$C$32 -> 540 | J116: =(F116*G116*H116)/$C$32 -> 1.2
B117: 10 | C117: Dr A.S Bajomo | F117: 4639.852 | G117: 0.12 | H117: 1 | I117: =J117*$C$32 -> 556.78224 | J117: =(F117*G117*H117)/$C$32 -> 1.2372939
B118: 11 | C118: Mectech Motors | F118: 7347.672 | G118: 0.17 | H118: 1 | I118: =J118*$C$32 -> 1249.1042 | J118: =(F118*G118*H118)/$C$32 -> 2.7757872
B119: 12 | C119: Blue Hill | F119: 4480 | G119: 0.16 | H119: 1 | I119: =J119*$C$32 -> 716.8 | J119: =(F119*G119*H119)/$C$32 -> 1.5928889
B120: 13 | C120: Natasha Mohunlal | F120: 2613.6 | G120: 0.19 | H120: 1 | I120: =J120*$C$32 -> 496.584 | J120: =(F120*G120*H120)/$C$32 -> 1.10352
B121: 14 | C121: MMFS | F121: 4807 | G121: 0.1 | H121: 1 | I121: =J121*$C$32 -> 480.7 | J121: =(F121*G121*H121)/$C$32 -> 1.0682222
B122: 15 | C122: CN Freight | F122: 4708.216 | G122: 0.12 | H122: 1 | I122: =J122*$C$32 -> 564.98592 | J122: =(F122*G122*H122)/$C$32 -> 1.2555243
B123: 16 | C123: Promote Balance | F123: 496.8 | G123: 1 | H123: 1 | I123: =J123*$C$32 -> 496.8 | J123: =(F123*G123*H123)/$C$32 -> 1.104
B124: 17 | C124: Bophelong | F124: 2918.7 | G124: 1 | H124: 1 | I124: =J124*$C$32 -> 2918.7 | J124: =(F124*G124*H124)/$C$32 -> 6.486
B125: 18 | C125: Makhubela Incorporated | F125: 500 | G125: 1 | H125: 1 | I125: =J125*$C$32 -> 500 | J125: =(F125*G125*H125)/$C$32 -> 1.1111111
B126: 19 | C126: Maksure Risk Solutions | F126: 7781.4 | G126: 1 | H126: 1 | I126: =J126*$C$32 -> 7781.4 | J126: =(F126*G126*H126)/$C$32 -> 17.292
... B132: 25 | C132: Work co | F132: 993.6 | G132: 1 | H132: 1 | I132: =J132*$C$32 -> 993.6 | J132: =(F132*G132*H132)/$C$32 -> 2.208
I133: =J133*$C$32 -> 0 | J133: =(F133*G133*H133)/$C$32 -> 0
I134: =J134*$C$32 -> 0 | J134: =(F134*G134*H134)/$C$32 -> 0
C135: Once off Work: | I135: =J135*$C$32 -> 0 | J135: =(F135*G135*H135)/$C$32 -> 0
B136: 1 | C136: Jacas Trading | D136: CIPC Annual Returns and BO | F136: 2728.26 | G136: 1 | H136: 1 | I136: =J136*$C$32 -> 2728.26 | J136: =(F136*G136*H136)/$C$32 -> 6.0628
B137: 2 | C137: Natasha Mohunlal | D137: CIPC Annual Returns and BO | F137: 1336.96 | G137: 1 | H137: 1 | I137: =J137*$C$32 -> 1336.96 | J137: =(F137*G137*H137)/$C$32 -> 2.9710222
B138: 3 | C138: ACHRI | D138: Property Audit | F138: 3913.04 | G138: 1 | H138: 1 | I138: =J138*$C$32 -> 3913.04 | J138: =(F138*G138*H138)/$C$32 -> 8.6956444
B139: 4 | C139: GLN Properties (Pty) Ltd | D139: EMP201 Submissions (Jan 2026) | F139: 391.3 | G139: 1 | H139: 1 | I139: =J139*$C$32 -> 391.3 | J139: =(F139*G139*H139)/$C$32 -> 0.86955556
...

Sheet Lesego Jan - Dec '26
F3: Workflow Scheduling
B8: "A business is a commercial profitable enterprise that runs without you"
C10: Workflow Dashboard
B11: Senior Client Manager In Charge : | G11: Rudzi Mziki
B12: Team Name: | G12: Lesego Moncho
B14: Team Member: | D14: Lesego | G14: Role: | J14: Accounting Intern
C15: Analysis: | E15: Fees: | G15: Analysis: | K15: Hours:
C16: Annual Fee Budget | E16: =34000*12 -> 408000 | G16: Annual Budgeted Hours | K16: =E16/C32 -> 1632
C17: Scheduled Work and Jobs | E17: =+I70+I139+I208+I278+I348+I418+I488+I558+I628+I698+I768+I838 -> 14899.513 | G17: Scheduled Hours | K17: =+J70+J139+J208+J278+J348+J418+J488+J558+J628+J698+J768+J838 -> 59.598051
C18: Over (Under) Scheduled Work | E18: =E17-E16 -> -393100.49 | G18: Over (Under) Scheduled Work | K18: =K17-K16 -> -1572.4019
B20: Remaining Hours to Fill:
D21: January | E21: =J32 -> 83.201949 | F21: Apr | G21: =+J216 -> 129.2 | H21: July | I21: =+J426 -> 142.8 | J21: Oct | K21: =+J636 -> 156.4
D22: Feb | E22: =+J79 -> 136 | F22: May | G22: =+J286 -> 149.6 | H22: Aug | I22: =J496 -> 142.8 | J22: Nov | K22: =+J706 -> 136
D23: Mar | E23: =+J147 -> 142.8 | F23: June | G23: =+J356 -> 136 | H23: Sept | I23: =+J566 -> 142.8 | J23: Dec | K23: =+J776 -> 136
B25: Total Productivity Hours To Fill : | G25: =SUM(E21:E23)+SUM(G21:G23)+SUM(I21:I23)+SUM(K21:K23) -> 1633.6019
C30: Workflow Schedule for | E30: January | J30: 2026
C31: Charge Rate: | D31: Working Days in Month | F31: KPI % | G31: Hours per Day | H31: Monthly Budgeted Hours | I31: Total Scheduled Fees | J31: Hours Left
C32: 250 | D32: 21 | F32: 0.85 | G32: 8 | H32: =D32*G32*F32 -> 142.8 | I32: =I70 -> 14899.513 | J32: =H32-J70 -> 83.201949
C33: Entity Group \ Job Name | D33: Notes | F33: Estimated Fees for Job | G33: Team Members Job Completion % | H33: Pricing or Efficiency Override | I33: Budgeted WIP | J33: Job Budgeted Hrs | K33: Submission Date to client | L33: Accountants commnent on Due Date
C35: Monthly Recurring Work
C36: Management Accounts:
A37: ='Rudzi Jan - Dec ''26'!A37 -> 0 | B37: 1 | C37: Advocate Maputla | F37: ='Work Component Split'!F28 -> 25181.84 | G37: ='Work Component Split'!I28 -> 0.50000007 | H37: 1 | I37: =J37*$C$32 -> 12590.922 | J37: =(F37*G37*H37)/$C$32 -> 50.363687
B38: 2 | C38: Maxopani Holdings | F38: ='Work Component Split'!F10 -> 23085.91 | G38: 0.1 | H38: 1 | I38: =J38*$C$32 -> 2308.591 | J38: =(F38*G38*H38)/$C$32 -> 9.234364
C51: Once Off work:
B52: 1 | H52: 1 | I52: =J52*$C$32 -> 0 | J52: =(F52*G52*H52)/$C$32 -> 0
B53: 2 | H53: 1 | I53: =J53*$C$32 -> 0 | J53: =(F53*G53*H53)/$C$32 -> 0
B54: 4 | H54: 1 | I54: =J54*$C$32 -> 0 | J54: =(F54*G54*H54)/$C$32 -> 0
B55: 5 | H55: 1 | I55: =J55*$C$32 -> 0 | J55: =(F55*G55*H55)/$C$32 -> 0
B56: 6 | H56: 1 | I56: =J56*$C$32 -> 0 | J56: =(F56*G56*H56)/$C$32 -> 0
B57: 7 | H57: 1 | I57: =J57*$C$32 -> 0 | J57: =(F57*G57*H57)/$C$32 -> 0
B58: 8 | H58: 1 | I58: =J58*$C$32 -> 0 | J58: =(F58*G58*H58)/$C$32 -> 0
B59: 9 | H59: 1 | I59: =J59*$C$32 -> 0 | J59: =(F59*G59*H59)/$C$32 -> 0
B60: 10 | H60: 1 | I60: =J60*$C$32 -> 0 | J60: =(F60*G60*H60)/$C$32 -> 0
B61: 11 | H61: 1 | I61: =J61*$C$32 -> 0 | J61: =(F61*G61*H61)/$C$32 -> 0
B62: 12 | H62: 1 | I62: =J62*$C$32 -> 0 | J62: =(F62*G62*H62)/$C$32 -> 0
B63: 13 | H63: 1 | I63: =J63*$C$32 -> 0 | J63: =(F63*G63*H63)/$C$32 -> 0
... B68: 20 | H68: 1 | I68: =J68*$C$32 -> 0 | J68: =(F68*G68*H68)/$C$32 -> 0
F70: =SUM(F37:F69) -> 48267.75 | I70: =SUM(I35:I69) -> 14899.513 | J70: =SUM(J34:J69) -> 59.598051
E71: Excl VAT | F71: =100/115*F70 -> 41971.957 | H71: Excl VAT | I71: =100/115*I70 -> 12956.098
C77: Workflow Schedule for | E77: February | J77: 2026
C78: Charge Rate: | D78: Working Days in Month | F78: KPI % | G78: Hours per Day | H78: Monthly Budgeted Hours | I78: Total Scheduled Fees | J78: Hours Left
C79: =C32 -> 250 | D79: 20 | F79: =F32 -> 0.85 | G79: =G32 -> 8 | H79: =D79*G79*F79 -> 136 | I79: =I139 -> 0 | J79: =H79-J139 -> 136
C80: Entity Group \ Job Name | D80: Notes | F80: Estimated Fees for Job | G80: Team Members Job Completion % | H80: Pricing or Efficiency Override | I80: Budgeted WIP | J80: Job Budgeted Hrs | K80: Submission Date to client | L80: Accountants commnent on Due Date
C82: Monthly Recurring Work
C83: Management Accounts:
B84: 1 | H84: 1 | I84: =J84*$C$32 -> 0 | J84: =(F84*G84*H84)/$C$32 -> 0
B85: 2 | H85: 1 | I85: =J85*$C$32 -> 0 | J85: =(F85*G85*H85)/$C$32 -> 0
B86: 3 | H86: 1 | I86: =J86*$C$32 -> 0 | J86: =(F86*G86*H86)/$C$32 -> 0
B87: 4 | H87: 1 | I87: =J87*$C$32 -> 0 | J87: =(F87*G87*H87)/$C$32 -> 0
B88: 5 | H88: 1 | I88: =J88*$C$32 -> 0 | J88: =(F88*G88*H88)/$C$32 -> 0
B89: 6 | H89: 1 | I89: =J89*$C$32 -> 0 | J89: =(F89*G89*H89)/$C$32 -> 0
B90: 7 | H90: 1 | I90: =J90*$C$32 -> 0 | J90: =(F90*G90*H90)/$C$32 -> 0
B91: 8 | H91: 1 | I91: =J91*$C$32 -> 0 | J91: =(F91*G91*H91)/$C$32 -> 0
B92: 9 | H92: 1 | I92: =J92*$C$32 -> 0 | J92: =(F92*G92*H92)/$C$32 -> 0
B93: 10 | H93: 1 | I93: =J93*$C$32 -> 0 | J93: =(F93*G93*H93)/$C$32 -> 0
C96: Payroll:
B97: 1 | H97: 1 | I97: =J97*$C$32 -> 0 | J97: =(F97*G97*H97)/$C$32 -> 0
B98: 2 | H98: 1 | I98: =J98*$C$32 -> 0 | J98: =(F98*G98*H98)/$C$32 -> 0
B99: 3 | H99: 1 | I99: =J99*$C$32 -> 0 | J99: =(F99*G99*H99)/$C$32 -> 0
B100: 4 | H100: 1 | I100: =J100*$C$32 -> 0 | J100: =(F100*G100*H100)/$C$32 -> 0
B101: 5 | H101: 1 | I101: =J101*$C$32 -> 0 | J101: =(F101*G101*H101)/$C$32 -> 0
B102: 6 | H102: 1 | I102: =J102*$C$32 -> 0 | J102: =(F102*G102*H102)/$C$32 -> 0
B103: 7 | H103: 1 | I103: =J103*$C$32 -> 0 | J103: =(F103*G103*H103)/$C$32 -> 0
B104: 8 | H104: 1 | I104: =J104*$C$32 -> 0 | J104: =(F104*G104*H104)/$C$32 -> 0
B105: 9 | H105: 1 | I105: =J105*$C$32 -> 0 | J105: =(F105*G105*H105)/$C$32 -> 0
B106: 10 | H106: 1 | I106: =J106*$C$32 -> 0 | J106: =(F106*G106*H106)/$C$32 -> 0
B107: 11 | H107: 1 | I107: =J107*$C$32 -> 0 | J107: =(F107*G107*H107)/$C$32 -> 0
B108: 12 | H108: 1 | I108: =J108*$C$32 -> 0 | J108: =(F108*G108*H108)/$C$32 -> 0
... B116: 20 | H116: 1 | I116: =J116*$C$32 -> 0 | J116: =(F116*G116*H116)/$C$32 -> 0
C119: Once Off work:
B120: 1 | H120: 1 | I120: =J120*$C$32 -> 0 | J120: =(F120*G120*H120)/$C$32 -> 0
B121: 2 | H121: 1 | I121: =J121*$C$32 -> 0 | J121: =(F121*G121*H121)/$C$32 -> 0
B122: 3 | H122: 1 | I122: =J122*$C$32 -> 0 | J122: =(F122*G122*H122)/$C$32 -> 0
B123: 4 | H123: 1 | I123: =J123*$C$32 -> 0 | J123: =(F123*G123*H123)/$C$32 -> 0
B124: 5 | H124: 1 | I124: =J124*$C$32 -> 0 | J124: =(F124*G124*H124)/$C$32 -> 0
B125: 7 | H125: 1 | I125: =J125*$C$32 -> 0 | J125: =(F125*G125*H125)/$C$32 -> 0
B126: 8 | H126: 1 | I126: =J126*$C$32 -> 0 | J126: =(F126*G126*H126)/$C$32 -> 0
B127: 9 | H127: 1 | I127: =J127*$C$32 -> 0 | J127: =(F127*G127*H127)/$C$32 -> 0
B128: 10 | H128: 1 | I128: =J128*$C$32 -> 0 | J128: =(F128*G128*H128)/$C$32 -> 0
B129: 11 | H129: 1
B130: 12 | H130: 1
B131: 14 | H131: 1 | I131: =J131*$C$32 -> 0 | J131: =(F131*G131*H131)/$C$32 -> 0
B132: 15 | H132: 1 | I132: =J132*$C$32 -> 0 | J132: =(F132*G132*H132)/$C$32 -> 0
B133: 16 | H133: 1 | I133: =J133*$C$32 -> 0 | J133: =(F133*G133*H133)/$C$32 -> 0
B134: 17 | H134: 1 | I134: =J134*$C$32 -> 0 | J134: =(F134*G134*H134)/$C$32 -> 0
B135: 18 | H135: 1 | I135: =J135*$C$32 -> 0 | J135: =(F135*G135*H135)/$C$32 -> 0
B136: 19 | H136: 1 | I136: =J136*$C$32 -> 0 | J136: =(F136*G136*H136)/$C$32 -> 0
B137: 20 | H137: 1 | I137: =J137*$C$32 -> 0 | J137: =(F137*G137*H137)/$C$32 -> 0
F139: =SUM(F82:F138) -> 0 | I139: =SUM(I84:I138) -> 0 | J139: =SUM(J81:J138) -> 0
E140: Excl VAT | F140: =100/115*F139 -> 0 | H140: Excl VAT | I140: =100/115*I139 -> 0
C145: Workflow Schedule for | E145: March | J145: 2026
C146: Charge Rate: | D146: Working Days in Month | F146: KPI % | G146: Hours per Day | H146: Monthly Budgeted Hours | I146: Total Scheduled Fees | J146: Hours Left
C147: =C79 -> 250 | D147: 21 | F147: =F79 -> 0.85 | G147: =G79 -> 8 | H147: =D147*G147*F147 -> 142.8 | I147: =I208 -> 0 | J147: =H147-J208 -> 142.8
C148: Entity Group \ Job Name | D148: Notes | F148: Estimated Fees for Job | G148: Team Members Job Completion % | H148: Pricing or Efficiency Override | I148: Budgeted WIP | J148: Job Budgeted Hrs | K148: Submission Date to client | L148: Accountants commnent on Due Date
C150: Monthly Recurring Work
C151: Mamangement Accounts:
B152: 1 | H152: 1 | I152: =J152*$C$32 -> 0 | J152: =(F152*G152*H152)/$C$32 -> 0
B153: 2 | H153: 1 | I153: =J153*$C$32 -> 0 | J153: =(F153*G153*H153)/$C$32 -> 0
B154: 3 | H154: 1 | I154: =J154*$C$32 -> 0 | J154: =(F154*G154*H154)/$C$32 -> 0
B155: 4 | H155: 1 | I155: =J155*$C$32 -> 0 | J155: =(F155*G155*H155)/$C$32 -> 0
...

Sheet Simelinkosi Jan - Dec '26
F3: Workflow Scheduling
B8: "A business is a commercial profitable enterprise that runs without you"
C10: Workflow Dashboard
B11: Senior Client Manager In Charge : | G11: Bruce Saurombe
B12: Team Name: | G12: Simelinkosi Kariga
B14: Team Member: | D14: Simelinkosi | G14: Role: | J14: Bookkeeper
C15: Analysis: | E15: Fees: | G15: Analysis: | K15: Hours:
C16: Annual Fee Budget | E16: =50512*12 -> 606144 | G16: Annual Budgeted Hours | K16: =E16/C32 -> 2424.576
C17: Scheduled Work and Jobs | E17: =+I71+I140+I209+I279+I349+I419+I489+I559+I629+I699+I769+I839 -> 17076.655 | G17: Scheduled Hours | K17: =+J71+J140+J209+J279+J349+J419+J489+J559+J629+J699+J769+J839 -> 68.306619
C18: Over (Under) Scheduled Work | E18: =E17-E16 -> -589067.35 | G18: Over (Under) Scheduled Work | K18: =K17-K16 -> -2356.2694
B20: Remaining Hours to Fill:
D21: January | E21: =J32 -> 57.693381 | F21: Apr | G21: =+J217 -> 114 | H21: July | I21: =+J427 -> 126 | J21: Oct | K21: =+J637 -> 138
D22: Feb | E22: =+J80 -> 120 | F22: May | G22: =+J287 -> 132 | H22: Aug | I22: =J497 -> 126 | J22: Nov | K22: =+J707 -> 120
D23: Mar | E23: =+J148 -> 126 | F23: June | G23: =+J357 -> 120 | H23: Sept | I23: =+J567 -> 126 | J23: Dec | K23: =+J777 -> 120
B25: Total Productivity Hours To Fill : | G25: =SUM(E21:E23)+SUM(G21:G23)+SUM(I21:I23)+SUM(K21:K23) -> 1425.6934
C30: Workflow Schedule for | E30: January | J30: 2026
C31: Charge Rate: | D31: Working Days in Month | F31: KPI % | G31: Hours per Day | H31: Monthly Budgeted Hours | I31: Total Scheduled Fees | J31: Hours Left
C32: 250 | D32: 21 | F32: 0.75 | G32: 8 | H32: =D32*G32*F32 -> 126 | I32: =I71 -> 17076.655 | J32: =H32-J71 -> 57.693381
C33: Entity Group \ Job Name | D33: Notes | F33: Estimated Fees for Job | G33: Team Members Job Completion % | H33: Pricing or Efficiency Override | I33: Budgeted WIP | J33: Job Budgeted Hrs | K33: Submission Date to client | L33: Accountants commnent on Due Date
C35: Monthly Recurring Work
C36: Management Accounts:
B37: 1 | C37: Fitness Reenvisioned | F37: ='Work Component Split'!F40 -> 1572.1 | G37: ='Work Component Split'!I40 -> 0.50000138 | H37: 1 | I37: =J37*$C$32 -> 786.05217 | J37: =(F37*G37*H37)/$C$32 -> 3.1442087
B38: 2 | C38: Luk Capital | F38: ='Work Component Split'!F41 -> 2596.51 | G38: ='Work Component Split'!I41 -> 0.49999958 | H38: 1 | I38: =J38*$C$32 -> 1298.2539 | J38: =(F38*G38*H38)/$C$32 -> 5.1930157
B39: 3 | C39: Moja Legal Consulting and Investment (Pty) Ltd | F39: ='Work Component Split'!F42 -> 2028.52 | G39: ='Work Component Split'!I42 -> 0.50000043 | H39: 1 | I39: =J39*$C$32 -> 1014.2609 | J39: =(F39*G39*H39)/$C$32 -> 4.0570435
B40: 4 | C40: Vera Step | F40: ='Work Component Split'!F43 -> 2943 | G40: ='Work Component Split'!I43 -> 0.5 | H40: 1 | I40: =J40*$C$32 -> 1471.5 | J40: =(F40*G40*H40)/$C$32 -> 5.886
B41: 5 | C41: Natasha Mohunlal | F41: ='Work Component Split'!F44 -> 2272.7 | G41: ='Work Component Split'!I44 -> 0.4049579 | H41: 1 | I41: =J41*$C$32 -> 920.34783 | J41: =(F41*G41*H41)/$C$32 -> 3.6813913
B42: 6 | C42: Swiiff | F42: ='Work Component Split'!F45 -> 2916 | G42: ='Work Component Split'!I45 -> 0.5 | H42: 1 | I42: =J42*$C$32 -> 1458 | J42: =(F42*G42*H42)/$C$32 -> 5.832
A43: every 6 months | B43: 7 | C43: Mawela Simpson | F43: ='Work Component Split'!F46 -> 3888 | G43: ='Work Component Split'!I46 -> 0.5 | H43: 1 | I43: =J43*$C$32 -> 1944 | J43: =(F43*G43*H43)/$C$32 -> 7.776
A44: every 2 months | B44: 8 | C44: MGI Global | F44: ='Work Component Split'!F47 -> 2916 | G44: ='Work Component Split'!I47 -> 0.5 | H44: 1 | I44: =J44*$C$32 -> 1458 | J44: =(F44*G44*H44)/$C$32 -> 5.832
B45: 9 | C45: MMFS | F45: ='Work Component Split'!F48 -> 4180 | G45: ='Work Component Split'!I48 -> 0.45215311 | H45: 1 | I45: =J45*$C$32 -> 1890 | J45: =(F45*G45*H45)/$C$32 -> 7.56
B46: 10 | C46: Bona By Wenzy | F46: ='Work Component Split'!F49 -> 1890 | G46: ='Work Component Split'!I49 -> 0.5 | H46: 1 | I46: =J46*$C$32 -> 945 | J46: =(F46*G46*H46)/$C$32 -> 3.78
B47: 11 | C47: Recovery Advisors | F47: ='Work Component Split'!F50 -> 2430 | G47: ='Work Component Split'!I50 -> 0.5 | H47: 1 | I47: =J47*$C$32 -> 1215 | J47: =(F47*G47*H47)/$C$32 -> 4.86
B48: 12 | C48: Subtream | F48: ='Work Component Split'!F51 -> 5352.48 | G48: ='Work Component Split'!I51 -> 0.5 | H48: 1 | I48: =J48*$C$32 -> 2676.24 | J48: =(F48*G48*H48)/$C$32 -> 10.70496
B49: 13 | C49: Plush Spaces | F49: ='Work Component Split'!F52 -> 2303.5043 | G49: 0 | H49: 1 | I49: =J49*$C$32 -> 0 | J49: =(F49*G49*H49)/$C$32 -> 0
C52: Once Off work:
B53: 1 | H53: 1 | I53: =J53*$C$32 -> 0 | J53: =(F53*G53*H53)/$C$32 -> 0
B54: 2 | H54: 1 | I54: =J54*$C$32 -> 0 | J54: =(F54*G54*H54)/$C$32 -> 0
B55: 4 | H55: 1 | I55: =J55*$C$32 -> 0 | J55: =(F55*G55*H55)/$C$32 -> 0
B56: 5 | H56: 1 | I56: =J56*$C$32 -> 0 | J56: =(F56*G56*H56)/$C$32 -> 0
B57: 6 | H57: 1 | I57: =J57*$C$32 -> 0 | J57: =(F57*G57*H57)/$C$32 -> 0
B58: 7 | H58: 1 | I58: =J58*$C$32 -> 0 | J58: =(F58*G58*H58)/$C$32 -> 0
B59: 8 | H59: 1 | I59: =J59*$C$32 -> 0 | J59: =(F59*G59*H59)/$C$32 -> 0
B60: 9 | H60: 1 | I60: =J60*$C$32 -> 0 | J60: =(F60*G60*H60)/$C$32 -> 0
B61: 10 | H61: 1 | I61: =J61*$C$32 -> 0 | J61: =(F61*G61*H61)/$C$32 -> 0
B62: 11 | H62: 1 | I62: =J62*$C$32 -> 0 | J62: =(F62*G62*H62)/$C$32 -> 0
B63: 12 | H63: 1 | I63: =J63*$C$32 -> 0 | J63: =(F63*G63*H63)/$C$32 -> 0
B64: 13 | H64: 1 | I64: =J64*$C$32 -> 0 | J64: =(F64*G64*H64)/$C$32 -> 0
... B69: 20 | H69: 1 | I69: =J69*$C$32 -> 0 | J69: =(F69*G69*H69)/$C$32 -> 0
F71: =SUM(F37:F70) -> 37288.814 | I71: =SUM(I35:I70) -> 17076.655 | J71: =SUM(J34:J70) -> 68.306619
E72: Excl VAT | F72: =100/115*F71 -> 32425.056 | H72: Excl VAT | I72: =100/115*I71 -> 14849.265
C78: Workflow Schedule for | E78: February | J78: 2026
C79: Charge Rate: | D79: Working Days in Month | F79: KPI % | G79: Hours per Day | H79: Monthly Budgeted Hours | I79: Total Scheduled Fees | J79: Hours Left
C80: =C32 -> 250 | D80: 20 | F80: =F32 -> 0.75 | G80: =G32 -> 8 | H80: =D80*G80*F80 -> 120 | I80: =I140 -> 0 | J80: =H80-J140 -> 120
C81: Entity Group \ Job Name | D81: Notes | F81: Estimated Fees for Job | G81: Team Members Job Completion % | H81: Pricing or Efficiency Override | I81: Budgeted WIP | J81: Job Budgeted Hrs | K81: Submission Date to client | L81: Accountants commnent on Due Date
C83: Monthly Recurring Work
C84: Management Accounts:
B85: 1 | H85: 1 | I85: =J85*$C$32 -> 0 | J85: =(F85*G85*H85)/$C$32 -> 0
B86: 2 | H86: 1 | I86: =J86*$C$32 -> 0 | J86: =(F86*G86*H86)/$C$32 -> 0
B87: 3 | H87: 1 | I87: =J87*$C$32 -> 0 | J87: =(F87*G87*H87)/$C$32 -> 0
B88: 4 | H88: 1 | I88: =J88*$C$32 -> 0 | J88: =(F88*G88*H88)/$C$32 -> 0
B89: 5 | H89: 1 | I89: =J89*$C$32 -> 0 | J89: =(F89*G89*H89)/$C$32 -> 0
B90: 6 | H90: 1 | I90: =J90*$C$32 -> 0 | J90: =(F90*G90*H90)/$C$32 -> 0
B91: 7 | H91: 1 | I91: =J91*$C$32 -> 0 | J91: =(F91*G91*H91)/$C$32 -> 0
B92: 8 | H92: 1 | I92: =J92*$C$32 -> 0 | J92: =(F92*G92*H92)/$C$32 -> 0
B93: 9 | H93: 1 | I93: =J93*$C$32 -> 0 | J93: =(F93*G93*H93)/$C$32 -> 0
B94: 10 | H94: 1 | I94: =J94*$C$32 -> 0 | J94: =(F94*G94*H94)/$C$32 -> 0
C97: Payroll:
B98: 1 | H98: 1 | I98: =J98*$C$32 -> 0 | J98: =(F98*G98*H98)/$C$32 -> 0
B99: 2 | H99: 1 | I99: =J99*$C$32 -> 0 | J99: =(F99*G99*H99)/$C$32 -> 0
B100: 3 | H100: 1 | I100: =J100*$C$32 -> 0 | J100: =(F100*G100*H100)/$C$32 -> 0
B101: 4 | H101: 1 | I101: =J101*$C$32 -> 0 | J101: =(F101*G101*H101)/$C$32 -> 0
B102: 5 | H102: 1 | I102: =J102*$C$32 -> 0 | J102: =(F102*G102*H102)/$C$32 -> 0
B103: 6 | H103: 1 | I103: =J103*$C$32 -> 0 | J103: =(F103*G103*H103)/$C$32 -> 0
B104: 7 | H104: 1 | I104: =J104*$C$32 -> 0 | J104: =(F104*G104*H104)/$C$32 -> 0
B105: 8 | H105: 1 | I105: =J105*$C$32 -> 0 | J105: =(F105*G105*H105)/$C$32 -> 0
B106: 9 | H106: 1 | I106: =J106*$C$32 -> 0 | J106: =(F106*G106*H106)/$C$32 -> 0
B107: 10 | H107: 1 | I107: =J107*$C$32 -> 0 | J107: =(F107*G107*H107)/$C$32 -> 0
B108: 11 | H108: 1 | I108: =J108*$C$32 -> 0 | J108: =(F108*G108*H108)/$C$32 -> 0
B109: 12 | H109: 1 | I109: =J109*$C$32 -> 0 | J109: =(F109*G109*H109)/$C$32 -> 0
... B117: 20 | H117: 1 | I117: =J117*$C$32 -> 0 | J117: =(F117*G117*H117)/$C$32 -> 0
C120: Once Off work:
B121: 1 | H121: 1 | I121: =J121*$C$32 -> 0 | J121: =(F121*G121*H121)/$C$32 -> 0
B122: 2 | H122: 1 | I122: =J122*$C$32 -> 0 | J122: =(F122*G122*H122)/$C$32 -> 0
B123: 3 | H123: 1 | I123: =J123*$C$32 -> 0 | J123: =(F123*G123*H123)/$C$32 -> 0
B124: 4 | H124: 1 | I124: =J124*$C$32 -> 0 | J124: =(F124*G124*H124)/$C$32 -> 0
B125: 5 | H125: 1 | I125: =J125*$C$32 -> 0 | J125: =(F125*G125*H125)/$C$32 -> 0
B126: 7 | H126: 1 | I126: =J126*$C$32 -> 0 | J126: =(F126*G126*H126)/$C$32 -> 0
B127: 8 | H127: 1 | I127: =J127*$C$32 -> 0 | J127: =(F127*G127*H127)/$C$32 -> 0
B128: 9 | H128: 1 | I128: =J128*$C$32 -> 0 | J128: =(F128*G128*H128)/$C$32 -> 0
B129: 10 | H129: 1 | I129: =J129*$C$32 -> 0 | J129: =(F129*G129*H129)/$C$32 -> 0
B130: 11 | H130: 1
B131: 12 | H131: 1
B132: 14 | H132: 1 | I132: =J132*$C$32 -> 0 | J132: =(F132*G132*H132)/$C$32 -> 0
B133: 15 | H133: 1 | I133: =J133*$C$32 -> 0 | J133: =(F133*G133*H133)/$C$32 -> 0
B134: 16 | H134: 1 | I134: =J134*$C$32 -> 0 | J134: =(F134*G134*H134)/$C$32 -> 0
B135: 17 | H135: 1 | I135: =J135*$C$32 -> 0 | J135: =(F135*G135*H135)/$C$32 -> 0
B136: 18 | H136: 1 | I136: =J136*$C$32 -> 0 | J136: =(F136*G136*H136)/$C$32 -> 0
B137: 19 | H137: 1 | I137: =J137*$C$32 -> 0 | J137: =(F137*G137*H137)/$C$32 -> 0
B138: 20 | H138: 1 | I138: =J138*$C$32 -> 0 | J138: =(F138*G138*H138)/$C$32 -> 0
F140: =SUM(F83:F139) -> 0 | I140: =SUM(I85:I139) -> 0 | J140: =SUM(J82:J139) -> 0
...

Sheet Mavis Jan - Dec '26
F3: Workflow Scheduling
B8: "A business is a commercial profitable enterprise that runs without you"
C10: Workflow Dashboard
B11: Senior Client Manager In Charge : | G11: Kenneth Mashava
B12: Team Name: | G12: Mavis Bincent
B14: Team Member: | D14: Mavis | G14: Role: | J14: Bookkeeper
C15: Analysis: | E15: Fees: | G15: Analysis: | K15: Hours:
C16: Annual Fee Budget | E16: =50512*12 -> 606144 | G16: Annual Budgeted Hours | K16: =E16/C32 -> 2424.576
C17: Scheduled Work and Jobs | E17: =+I70+I139+I208+I278+I348+I418+I488+I558+I628+I698+I768+I838 -> 14675.77 | G17: Scheduled Hours | K17: =+J70+J139+J208+J278+J348+J418+J488+J558+J628+J698+J768+J838 -> 58.703078
C18: Over (Under) Scheduled Work | E18: =E17-E16 -> -591468.23 | G18: Over (Under) Scheduled Work | K18: =K17-K16 -> -2365.8729
B20: Remaining Hours to Fill:
D21: January | E21: =J32 -> 67.296922 | F21: Apr | G21: =+J216 -> 114 | H21: July | I21: =+J426 -> 126 | J21: Oct | K21: =+J636 -> 138
D22: Feb | E22: =+J79 -> 120 | F22: May | G22: =+J286 -> 132 | H22: Aug | I22: =J496 -> 126 | J22: Nov | K22: =+J706 -> 120
D23: Mar | E23: =+J147 -> 126 | F23: June | G23: =+J356 -> 120 | H23: Sept | I23: =+J566 -> 126 | J23: Dec | K23: =+J776 -> 120
B25: Total Productivity Hours To Fill : | G25: =SUM(E21:E23)+SUM(G21:G23)+SUM(I21:I23)+SUM(K21:K23) -> 1435.2969
C30: Workflow Schedule for | E30: January | J30: 2026
C31: Charge Rate: | D31: Working Days in Month | F31: KPI % | G31: Hours per Day | H31: Monthly Budgeted Hours | I31: Total Scheduled Fees | J31: Hours Left
C32: 250 | D32: 21 | F32: 0.75 | G32: 8 | H32: =D32*G32*F32 -> 126 | I32: =I70 -> 14675.77 | J32: =H32-J70 -> 67.296922
C33: Entity Group \ Job Name | D33: Notes | F33: Estimated Fees for Job | G33: Team Members Job Completion % | H33: Pricing or Efficiency Override | I33: Budgeted WIP | J33: Job Budgeted Hrs | K33: Submission Date to client | L33: Accountants commnent on Due Date
C35: Monthly Recurring Work
C36: Management Accounts:
B37: 1 | C37: Innovateher | F37: ='Work Component Split'!F12 -> 24734.36 | G37: ='Work Component Split'!I12 -> 0.49999994 | H37: 1 | I37: =J37*$C$32 -> 12367.179 | J37: =(F37*G37*H37)/$C$32 -> 49.468714
B38: 2 | C38: Maxopani Holdings | F38: ='Work Component Split'!F10 -> 23085.91 | G38: 0.1 | H38: 1 | I38: =J38*$C$32 -> 2308.591 | J38: =(F38*G38*H38)/$C$32 -> 9.234364
C51: Once Off work:
B52: 1 | H52: 1 | I52: =J52*$C$32 -> 0 | J52: =(F52*G52*H52)/$C$32 -> 0
B53: 2 | H53: 1 | I53: =J53*$C$32 -> 0 | J53: =(F53*G53*H53)/$C$32 -> 0
B54: 4 | H54: 1 | I54: =J54*$C$32 -> 0 | J54: =(F54*G54*H54)/$C$32 -> 0
B55: 5 | H55: 1 | I55: =J55*$C$32 -> 0 | J55: =(F55*G55*H55)/$C$32 -> 0
B56: 6 | H56: 1 | I56: =J56*$C$32 -> 0 | J56: =(F56*G56*H56)/$C$32 -> 0
B57: 7 | H57: 1 | I57: =J57*$C$32 -> 0 | J57: =(F57*G57*H57)/$C$32 -> 0
B58: 8 | H58: 1 | I58: =J58*$C$32 -> 0 | J58: =(F58*G58*H58)/$C$32 -> 0
B59: 9 | H59: 1 | I59: =J59*$C$32 -> 0 | J59: =(F59*G59*H59)/$C$32 -> 0
B60: 10 | H60: 1 | I60: =J60*$C$32 -> 0 | J60: =(F60*G60*H60)/$C$32 -> 0
B61: 11 | H61: 1 | I61: =J61*$C$32 -> 0 | J61: =(F61*G61*H61)/$C$32 -> 0
B62: 12 | H62: 1 | I62: =J62*$C$32 -> 0 | J62: =(F62*G62*H62)/$C$32 -> 0
B63: 13 | H63: 1 | I63: =J63*$C$32 -> 0 | J63: =(F63*G63*H63)/$C$32 -> 0
... B68: 20 | H68: 1 | I68: =J68*$C$32 -> 0 | J68: =(F68*G68*H68)/$C$32 -> 0
F70: =SUM(F37:F69) -> 47820.27 | I70: =SUM(I35:I69) -> 14675.77 | J70: =SUM(J34:J69) -> 58.703078
E71: Excl VAT | F71: =100/115*F70 -> 41582.843 | H71: Excl VAT | I71: =100/115*I70 -> 12761.539
C77: Workflow Schedule for | E77: February | J77: 2026
C78: Charge Rate: | D78: Working Days in Month | F78: KPI % | G78: Hours per Day | H78: Monthly Budgeted Hours | I78: Total Scheduled Fees | J78: Hours Left
C79: =C32 -> 250 | D79: 20 | F79: =F32 -> 0.75 | G79: =G32 -> 8 | H79: =D79*G79*F79 -> 120 | I79: =I139 -> 0 | J79: =H79-J139 -> 120
C80: Entity Group \ Job Name | D80: Notes | F80: Estimated Fees for Job | G80: Team Members Job Completion % | H80: Pricing or Efficiency Override | I80: Budgeted WIP | J80: Job Budgeted Hrs | K80: Submission Date to client | L80: Accountants commnent on Due Date
C82: Monthly Recurring Work
C83: Management Accounts:
B84: 1 | H84: 1 | I84: =J84*$C$32 -> 0 | J84: =(F84*G84*H84)/$C$32 -> 0
B85: 2 | H85: 1 | I85: =J85*$C$32 -> 0 | J85: =(F85*G85*H85)/$C$32 -> 0
B86: 3 | H86: 1 | I86: =J86*$C$32 -> 0 | J86: =(F86*G86*H86)/$C$32 -> 0
B87: 4 | H87: 1 | I87: =J87*$C$32 -> 0 | J87: =(F87*G87*H87)/$C$32 -> 0
B88: 5 | H88: 1 | I88: =J88*$C$32 -> 0 | J88: =(F88*G88*H88)/$C$32 -> 0
B89: 6 | H89: 1 | I89: =J89*$C$32 -> 0 | J89: =(F89*G89*H89)/$C$32 -> 0
B90: 7 | H90: 1 | I90: =J90*$C$32 -> 0 | J90: =(F90*G90*H90)/$C$32 -> 0
B91: 8 | H91: 1 | I91: =J91*$C$32 -> 0 | J91: =(F91*G91*H91)/$C$32 -> 0
B92: 9 | H92: 1 | I92: =J92*$C$32 -> 0 | J92: =(F92*G92*H92)/$C$32 -> 0
B93: 10 | H93: 1 | I93: =J93*$C$32 -> 0 | J93: =(F93*G93*H93)/$C$32 -> 0
C96: Payroll:
B97: 1 | H97: 1 | I97: =J97*$C$32 -> 0 | J97: =(F97*G97*H97)/$C$32 -> 0
B98: 2 | H98: 1 | I98: =J98*$C$32 -> 0 | J98: =(F98*G98*H98)/$C$32 -> 0
B99: 3 | H99: 1 | I99: =J99*$C$32 -> 0 | J99: =(F99*G99*H99)/$C$32 -> 0
B100: 4 | H100: 1 | I100: =J100*$C$32 -> 0 | J100: =(F100*G100*H100)/$C$32 -> 0
B101: 5 | H101: 1 | I101: =J101*$C$32 -> 0 | J101: =(F101*G101*H101)/$C$32 -> 0
B102: 6 | H102: 1 | I102: =J102*$C$32 -> 0 | J102: =(F102*G102*H102)/$C$32 -> 0
B103: 7 | H103: 1 | I103: =J103*$C$32 -> 0 | J103: =(F103*G103*H103)/$C$32 -> 0
B104: 8 | H104: 1 | I104: =J104*$C$32 -> 0 | J104: =(F104*G104*H104)/$C$32 -> 0
B105: 9 | H105: 1 | I105: =J105*$C$32 -> 0 | J105: =(F105*G105*H105)/$C$32 -> 0
B106: 10 | H106: 1 | I106: =J106*$C$32 -> 0 | J106: =(F106*G106*H106)/$C$32 -> 0
B107: 11 | H107: 1 | I107: =J107*$C$32 -> 0 | J107: =(F107*G107*H107)/$C$32 -> 0
B108: 12 | H108: 1 | I108: =J108*$C$32 -> 0 | J108: =(F108*G108*H108)/$C$32 -> 0
... B116: 20 | H116: 1 | I116: =J116*$C$32 -> 0 | J116: =(F116*G116*H116)/$C$32 -> 0
C119: Once Off work:
B120: 1 | H120: 1 | I120: =J120*$C$32 -> 0 | J120: =(F120*G120*H120)/$C$32 -> 0
B121: 2 | H121: 1 | I121: =J121*$C$32 -> 0 | J121: =(F121*G121*H121)/$C$32 -> 0
B122: 3 | H122: 1 | I122: =J122*$C$32 -> 0 | J122: =(F122*G122*H122)/$C$32 -> 0
B123: 4 | H123: 1 | I123: =J123*$C$32 -> 0 | J123: =(F123*G123*H123)/$C$32 -> 0
B124: 5 | H124: 1 | I124: =J124*$C$32 -> 0 | J124: =(F124*G124*H124)/$C$32 -> 0
B125: 7 | H125: 1 | I125: =J125*$C$32 -> 0 | J125: =(F125*G125*H125)/$C$32 -> 0
B126: 8 | H126: 1 | I126: =J126*$C$32 -> 0 | J126: =(F126*G126*H126)/$C$32 -> 0
B127: 9 | H127: 1 | I127: =J127*$C$32 -> 0 | J127: =(F127*G127*H127)/$C$32 -> 0
B128: 10 | H128: 1 | I128: =J128*$C$32 -> 0 | J128: =(F128*G128*H128)/$C$32 -> 0
B129: 11 | H129: 1
B130: 12 | H130: 1
B131: 14 | H131: 1 | I131: =J131*$C$32 -> 0 | J131: =(F131*G131*H131)/$C$32 -> 0
B132: 15 | H132: 1 | I132: =J132*$C$32 -> 0 | J132: =(F132*G132*H132)/$C$32 -> 0
B133: 16 | H133: 1 | I133: =J133*$C$32 -> 0 | J133: =(F133*G133*H133)/$C$32 -> 0
B134: 17 | H134: 1 | I134: =J134*$C$32 -> 0 | J134: =(F134*G134*H134)/$C$32 -> 0
B135: 18 | H135: 1 | I135: =J135*$C$32 -> 0 | J135: =(F135*G135*H135)/$C$32 -> 0
B136: 19 | H136: 1 | I136: =J136*$C$32 -> 0 | J136: =(F136*G136*H136)/$C$32 -> 0
B137: 20 | H137: 1 | I137: =J137*$C$32 -> 0 | J137: =(F137*G137*H137)/$C$32 -> 0
F139: =SUM(F82:F138) -> 0 | I139: =SUM(I84:I138) -> 0 | J139: =SUM(J81:J138) -> 0
E140: Excl VAT | F140: =100/115*F139 -> 0 | H140: Excl VAT | I140: =100/115*I139 -> 0
C145: Workflow Schedule for | E145: March | J145: 2026
C146: Charge Rate: | D146: Working Days in Month | F146: KPI % | G146: Hours per Day | H146: Monthly Budgeted Hours | I146: Total Scheduled Fees | J146: Hours Left
C147: =C79 -> 250 | D147: 21 | F147: =F79 -> 0.75 | G147: =G79 -> 8 | H147: =D147*G147*F147 -> 126 | I147: =I208 -> 0 | J147: =H147-J208 -> 126
C148: Entity Group \ Job Name | D148: Notes | F148: Estimated Fees for Job | G148: Team Members Job Completion % | H148: Pricing or Efficiency Override | I148: Budgeted WIP | J148: Job Budgeted Hrs | K148: Submission Date to client | L148: Accountants commnent on Due Date
C150: Monthly Recurring Work
C151: Mamangement Accounts:
B152: 1 | H152: 1 | I152: =J152*$C$32 -> 0 | J152: =(F152*G152*H152)/$C$32 -> 0
B153: 2 | H153: 1 | I153: =J153*$C$32 -> 0 | J153: =(F153*G153*H153)/$C$32 -> 0
B154: 3 | H154: 1 | I154: =J154*$C$32 -> 0 | J154: =(F154*G154*H154)/$C$32 -> 0
B155: 4 | H155: 1 | I155: =J155*$C$32 -> 0 | J155: =(F155*G155*H155)/$C$32 -> 0
...
